{
  "since": "2025-12-16T03:41:27Z",
  "total_runs": 181,
  "runs": [
    {
      "id": 20290571691,
      "name": ".github/workflows/daily-ltdd-telemetry.yml",
      "event": "push",
      "status": "completed",
      "conclusion": "failure",
      "created_at": "2025-12-17T03:26:26Z",
      "updated_at": "2025-12-17T03:26:26Z",
      "duration_ms": 0
    },
    {
      "id": 20290571845,
      "name": "Prod Guardrails",
      "event": "push",
      "status": "completed",
      "conclusion": "failure",
      "created_at": "2025-12-17T03:26:26Z",
      "updated_at": "2025-12-17T03:27:07Z",
      "duration_ms": 41000
    },
    {
      "id": 20290571846,
      "name": "Lock Tests (Production Sentinel)",
      "event": "push",
      "status": "completed",
      "conclusion": "failure",
      "created_at": "2025-12-17T03:26:26Z",
      "updated_at": "2025-12-17T03:28:59Z",
      "duration_ms": 153000
    },
    {
      "id": 20290571850,
      "name": "Release (Golden Path)",
      "event": "push",
      "status": "completed",
      "conclusion": "success",
      "created_at": "2025-12-17T03:26:26Z",
      "updated_at": "2025-12-17T03:35:58Z",
      "duration_ms": 572000
    },
    {
      "id": 20290571369,
      "name": ".github/workflows/hardening-gate.yml",
      "event": "push",
      "status": "completed",
      "conclusion": "failure",
      "created_at": "2025-12-17T03:26:25Z",
      "updated_at": "2025-12-17T03:26:25Z",
      "duration_ms": 0
    },
    {
      "id": 20290571459,
      "name": ".github/workflows/ltdd-sync-branch-protection.yml",
      "event": "push",
      "status": "completed",
      "conclusion": "failure",
      "created_at": "2025-12-17T03:26:25Z",
      "updated_at": "2025-12-17T03:26:25Z",
      "duration_ms": 0
    },
    {
      "id": 20290571571,
      "name": ".github/workflows/ci.yml",
      "event": "push",
      "status": "completed",
      "conclusion": "failure",
      "created_at": "2025-12-17T03:26:25Z",
      "updated_at": "2025-12-17T03:26:25Z",
      "duration_ms": 0
    },
    {
      "id": 20290484588,
      "name": ".github/workflows/ci.yml",
      "event": "push",
      "status": "completed",
      "conclusion": "failure",
      "created_at": "2025-12-17T03:21:25Z",
      "updated_at": "2025-12-17T03:21:25Z",
      "duration_ms": 0
    },
    {
      "id": 20290484271,
      "name": ".github/workflows/daily-ltdd-telemetry.yml",
      "event": "push",
      "status": "completed",
      "conclusion": "failure",
      "created_at": "2025-12-17T03:21:24Z",
      "updated_at": "2025-12-17T03:21:24Z",
      "duration_ms": 0
    },
    {
      "id": 20290484368,
      "name": ".github/workflows/hardening-gate.yml",
      "event": "push",
      "status": "completed",
      "conclusion": "failure",
      "created_at": "2025-12-17T03:21:24Z",
      "updated_at": "2025-12-17T03:21:24Z",
      "duration_ms": 0
    },
    {
      "id": 20290484444,
      "name": ".github/workflows/ltdd-sync-branch-protection.yml",
      "event": "push",
      "status": "completed",
      "conclusion": "failure",
      "created_at": "2025-12-17T03:21:24Z",
      "updated_at": "2025-12-17T03:21:24Z",
      "duration_ms": 0
    },
    {
      "id": 20290438953,
      "name": ".github/workflows/ltdd-sync-branch-protection.yml",
      "event": "push",
      "status": "completed",
      "conclusion": "failure",
      "created_at": "2025-12-17T03:18:55Z",
      "updated_at": "2025-12-17T03:18:55Z",
      "duration_ms": 0
    },
    {
      "id": 20290439125,
      "name": ".github/workflows/ci.yml",
      "event": "push",
      "status": "completed",
      "conclusion": "failure",
      "created_at": "2025-12-17T03:18:55Z",
      "updated_at": "2025-12-17T03:18:55Z",
      "duration_ms": 0
    },
    {
      "id": 20290438681,
      "name": ".github/workflows/daily-ltdd-telemetry.yml",
      "event": "push",
      "status": "completed",
      "conclusion": "failure",
      "created_at": "2025-12-17T03:18:54Z",
      "updated_at": "2025-12-17T03:18:54Z",
      "duration_ms": 0
    },
    {
      "id": 20290438804,
      "name": ".github/workflows/hardening-gate.yml",
      "event": "push",
      "status": "completed",
      "conclusion": "failure",
      "created_at": "2025-12-17T03:18:54Z",
      "updated_at": "2025-12-17T03:18:54Z",
      "duration_ms": 0
    },
    {
      "id": 20290423093,
      "name": ".github/workflows/ci.yml",
      "event": "push",
      "status": "completed",
      "conclusion": "failure",
      "created_at": "2025-12-17T03:18:00Z",
      "updated_at": "2025-12-17T03:18:00Z",
      "duration_ms": 0
    },
    {
      "id": 20290422675,
      "name": ".github/workflows/ltdd-sync-branch-protection.yml",
      "event": "push",
      "status": "completed",
      "conclusion": "failure",
      "created_at": "2025-12-17T03:17:59Z",
      "updated_at": "2025-12-17T03:17:59Z",
      "duration_ms": 0
    },
    {
      "id": 20290422806,
      "name": ".github/workflows/hardening-gate.yml",
      "event": "push",
      "status": "completed",
      "conclusion": "failure",
      "created_at": "2025-12-17T03:17:59Z",
      "updated_at": "2025-12-17T03:17:59Z",
      "duration_ms": 0
    },
    {
      "id": 20290422987,
      "name": ".github/workflows/daily-ltdd-telemetry.yml",
      "event": "push",
      "status": "completed",
      "conclusion": "failure",
      "created_at": "2025-12-17T03:17:59Z",
      "updated_at": "2025-12-17T03:17:59Z",
      "duration_ms": 0
    },
    {
      "id": 20289729585,
      "name": "Prod Guardrails",
      "event": "push",
      "status": "completed",
      "conclusion": "failure",
      "created_at": "2025-12-17T02:38:48Z",
      "updated_at": "2025-12-17T02:39:25Z",
      "duration_ms": 37000
    },
    {
      "id": 20289729597,
      "name": "Lock Tests (Production Sentinel)",
      "event": "push",
      "status": "completed",
      "conclusion": "failure",
      "created_at": "2025-12-17T02:38:48Z",
      "updated_at": "2025-12-17T02:41:26Z",
      "duration_ms": 158000
    },
    {
      "id": 20289729619,
      "name": "Release (Golden Path)",
      "event": "push",
      "status": "completed",
      "conclusion": "success",
      "created_at": "2025-12-17T02:38:48Z",
      "updated_at": "2025-12-17T02:48:48Z",
      "duration_ms": 600000
    },
    {
      "id": 20289729326,
      "name": ".github/workflows/daily-ltdd-telemetry.yml",
      "event": "push",
      "status": "completed",
      "conclusion": "failure",
      "created_at": "2025-12-17T02:38:47Z",
      "updated_at": "2025-12-17T02:38:47Z",
      "duration_ms": 0
    },
    {
      "id": 20289729412,
      "name": ".github/workflows/ci.yml",
      "event": "push",
      "status": "completed",
      "conclusion": "failure",
      "created_at": "2025-12-17T02:38:47Z",
      "updated_at": "2025-12-17T02:38:47Z",
      "duration_ms": 0
    },
    {
      "id": 20289729058,
      "name": ".github/workflows/hardening-gate.yml",
      "event": "push",
      "status": "completed",
      "conclusion": "failure",
      "created_at": "2025-12-17T02:38:46Z",
      "updated_at": "2025-12-17T02:38:46Z",
      "duration_ms": 0
    },
    {
      "id": 20289729199,
      "name": ".github/workflows/ltdd-sync-branch-protection.yml",
      "event": "push",
      "status": "completed",
      "conclusion": "failure",
      "created_at": "2025-12-17T02:38:46Z",
      "updated_at": "2025-12-17T02:38:46Z",
      "duration_ms": 0
    },
    {
      "id": 20289641162,
      "name": ".github/workflows/ci.yml",
      "event": "push",
      "status": "completed",
      "conclusion": "failure",
      "created_at": "2025-12-17T02:33:52Z",
      "updated_at": "2025-12-17T02:33:52Z",
      "duration_ms": 0
    },
    {
      "id": 20289640875,
      "name": ".github/workflows/ltdd-sync-branch-protection.yml",
      "event": "push",
      "status": "completed",
      "conclusion": "failure",
      "created_at": "2025-12-17T02:33:51Z",
      "updated_at": "2025-12-17T02:33:51Z",
      "duration_ms": 0
    },
    {
      "id": 20289640987,
      "name": ".github/workflows/hardening-gate.yml",
      "event": "push",
      "status": "completed",
      "conclusion": "failure",
      "created_at": "2025-12-17T02:33:51Z",
      "updated_at": "2025-12-17T02:33:51Z",
      "duration_ms": 0
    },
    {
      "id": 20289641080,
      "name": ".github/workflows/daily-ltdd-telemetry.yml",
      "event": "push",
      "status": "completed",
      "conclusion": "failure",
      "created_at": "2025-12-17T02:33:51Z",
      "updated_at": "2025-12-17T02:33:51Z",
      "duration_ms": 0
    },
    {
      "id": 20289545030,
      "name": ".github/workflows/ltdd-sync-branch-protection.yml",
      "event": "push",
      "status": "completed",
      "conclusion": "failure",
      "created_at": "2025-12-17T02:28:44Z",
      "updated_at": "2025-12-17T02:28:44Z",
      "duration_ms": 0
    },
    {
      "id": 20289545182,
      "name": ".github/workflows/ci.yml",
      "event": "push",
      "status": "completed",
      "conclusion": "failure",
      "created_at": "2025-12-17T02:28:44Z",
      "updated_at": "2025-12-17T02:28:44Z",
      "duration_ms": 0
    },
    {
      "id": 20289544838,
      "name": ".github/workflows/daily-ltdd-telemetry.yml",
      "event": "push",
      "status": "completed",
      "conclusion": "failure",
      "created_at": "2025-12-17T02:28:43Z",
      "updated_at": "2025-12-17T02:28:43Z",
      "duration_ms": 0
    },
    {
      "id": 20289544932,
      "name": ".github/workflows/hardening-gate.yml",
      "event": "push",
      "status": "completed",
      "conclusion": "failure",
      "created_at": "2025-12-17T02:28:43Z",
      "updated_at": "2025-12-17T02:28:43Z",
      "duration_ms": 0
    },
    {
      "id": 20285356679,
      "name": "Prod Guardrails",
      "event": "push",
      "status": "completed",
      "conclusion": "failure",
      "created_at": "2025-12-16T22:52:00Z",
      "updated_at": "2025-12-16T22:52:38Z",
      "duration_ms": 38000
    },
    {
      "id": 20285356496,
      "name": ".github/workflows/ci.yml",
      "event": "push",
      "status": "completed",
      "conclusion": "failure",
      "created_at": "2025-12-16T22:52:00Z",
      "updated_at": "2025-12-16T22:52:00Z",
      "duration_ms": 0
    },
    {
      "id": 20285356683,
      "name": "Lock Tests (Production Sentinel)",
      "event": "push",
      "status": "completed",
      "conclusion": "failure",
      "created_at": "2025-12-16T22:52:00Z",
      "updated_at": "2025-12-16T22:54:29Z",
      "duration_ms": 149000
    },
    {
      "id": 20285356675,
      "name": "Release (Golden Path)",
      "event": "push",
      "status": "completed",
      "conclusion": "success",
      "created_at": "2025-12-16T22:52:00Z",
      "updated_at": "2025-12-16T23:02:34Z",
      "duration_ms": 634000
    },
    {
      "id": 20285356097,
      "name": ".github/workflows/ltdd-sync-branch-protection.yml",
      "event": "push",
      "status": "completed",
      "conclusion": "failure",
      "created_at": "2025-12-16T22:51:59Z",
      "updated_at": "2025-12-16T22:51:59Z",
      "duration_ms": 0
    },
    {
      "id": 20285356236,
      "name": ".github/workflows/daily-ltdd-telemetry.yml",
      "event": "push",
      "status": "completed",
      "conclusion": "failure",
      "created_at": "2025-12-16T22:51:59Z",
      "updated_at": "2025-12-16T22:51:59Z",
      "duration_ms": 0
    },
    {
      "id": 20285356356,
      "name": ".github/workflows/hardening-gate.yml",
      "event": "push",
      "status": "completed",
      "conclusion": "failure",
      "created_at": "2025-12-16T22:51:59Z",
      "updated_at": "2025-12-16T22:51:59Z",
      "duration_ms": 0
    },
    {
      "id": 20285203296,
      "name": ".github/workflows/ci.yml",
      "event": "push",
      "status": "completed",
      "conclusion": "failure",
      "created_at": "2025-12-16T22:45:42Z",
      "updated_at": "2025-12-16T22:45:42Z",
      "duration_ms": 0
    },
    {
      "id": 20285203021,
      "name": ".github/workflows/daily-ltdd-telemetry.yml",
      "event": "push",
      "status": "completed",
      "conclusion": "failure",
      "created_at": "2025-12-16T22:45:42Z",
      "updated_at": "2025-12-16T22:45:42Z",
      "duration_ms": 0
    },
    {
      "id": 20285203159,
      "name": ".github/workflows/ltdd-sync-branch-protection.yml",
      "event": "push",
      "status": "completed",
      "conclusion": "failure",
      "created_at": "2025-12-16T22:45:42Z",
      "updated_at": "2025-12-16T22:45:42Z",
      "duration_ms": 0
    },
    {
      "id": 20285202899,
      "name": ".github/workflows/hardening-gate.yml",
      "event": "push",
      "status": "completed",
      "conclusion": "failure",
      "created_at": "2025-12-16T22:45:41Z",
      "updated_at": "2025-12-16T22:45:41Z",
      "duration_ms": 0
    },
    {
      "id": 20285128444,
      "name": "Ping (Actions Test)",
      "event": "push",
      "status": "completed",
      "conclusion": "success",
      "created_at": "2025-12-16T22:42:35Z",
      "updated_at": "2025-12-16T22:42:42Z",
      "duration_ms": 7000
    },
    {
      "id": 20285127840,
      "name": ".github/workflows/daily-ltdd-telemetry.yml",
      "event": "push",
      "status": "completed",
      "conclusion": "failure",
      "created_at": "2025-12-16T22:42:34Z",
      "updated_at": "2025-12-16T22:42:34Z",
      "duration_ms": 0
    },
    {
      "id": 20285128044,
      "name": ".github/workflows/hardening-gate.yml",
      "event": "push",
      "status": "completed",
      "conclusion": "failure",
      "created_at": "2025-12-16T22:42:34Z",
      "updated_at": "2025-12-16T22:42:34Z",
      "duration_ms": 0
    },
    {
      "id": 20285127499,
      "name": ".github/workflows/ci.yml",
      "event": "push",
      "status": "completed",
      "conclusion": "failure",
      "created_at": "2025-12-16T22:42:33Z",
      "updated_at": "2025-12-16T22:42:33Z",
      "duration_ms": 0
    },
    {
      "id": 20285127685,
      "name": ".github/workflows/ltdd-sync-branch-protection.yml",
      "event": "push",
      "status": "completed",
      "conclusion": "failure",
      "created_at": "2025-12-16T22:42:33Z",
      "updated_at": "2025-12-16T22:42:33Z",
      "duration_ms": 0
    },
    {
      "id": 20281615073,
      "name": "Lock Tests (Production Sentinel)",
      "event": "push",
      "status": "completed",
      "conclusion": "failure",
      "created_at": "2025-12-16T20:23:28Z",
      "updated_at": "2025-12-16T20:26:07Z",
      "duration_ms": 159000
    },
    {
      "id": 20281615087,
      "name": "Release (Golden Path)",
      "event": "push",
      "status": "completed",
      "conclusion": "success",
      "created_at": "2025-12-16T20:23:28Z",
      "updated_at": "2025-12-16T20:35:49Z",
      "duration_ms": 741000
    },
    {
      "id": 20281615098,
      "name": "Prod Guardrails",
      "event": "push",
      "status": "completed",
      "conclusion": "failure",
      "created_at": "2025-12-16T20:23:28Z",
      "updated_at": "2025-12-16T20:24:11Z",
      "duration_ms": 43000
    },
    {
      "id": 20281614639,
      "name": ".github/workflows/ltdd-sync-branch-protection.yml",
      "event": "push",
      "status": "completed",
      "conclusion": "failure",
      "created_at": "2025-12-16T20:23:27Z",
      "updated_at": "2025-12-16T20:23:27Z",
      "duration_ms": 0
    },
    {
      "id": 20281614838,
      "name": ".github/workflows/ci.yml",
      "event": "push",
      "status": "completed",
      "conclusion": "failure",
      "created_at": "2025-12-16T20:23:27Z",
      "updated_at": "2025-12-16T20:23:27Z",
      "duration_ms": 0
    },
    {
      "id": 20281614263,
      "name": ".github/workflows/daily-ltdd-telemetry.yml",
      "event": "push",
      "status": "completed",
      "conclusion": "failure",
      "created_at": "2025-12-16T20:23:26Z",
      "updated_at": "2025-12-16T20:23:26Z",
      "duration_ms": 0
    },
    {
      "id": 20281614470,
      "name": ".github/workflows/hardening-gate.yml",
      "event": "push",
      "status": "completed",
      "conclusion": "failure",
      "created_at": "2025-12-16T20:23:26Z",
      "updated_at": "2025-12-16T20:23:26Z",
      "duration_ms": 0
    },
    {
      "id": 20281443191,
      "name": "Ping (Actions Test)",
      "event": "push",
      "status": "completed",
      "conclusion": "success",
      "created_at": "2025-12-16T20:16:27Z",
      "updated_at": "2025-12-16T20:16:35Z",
      "duration_ms": 8000
    },
    {
      "id": 20281442899,
      "name": ".github/workflows/daily-ltdd-telemetry.yml",
      "event": "push",
      "status": "completed",
      "conclusion": "failure",
      "created_at": "2025-12-16T20:16:27Z",
      "updated_at": "2025-12-16T20:16:27Z",
      "duration_ms": 0
    },
    {
      "id": 20281442589,
      "name": ".github/workflows/ci.yml",
      "event": "push",
      "status": "completed",
      "conclusion": "failure",
      "created_at": "2025-12-16T20:16:26Z",
      "updated_at": "2025-12-16T20:16:26Z",
      "duration_ms": 0
    },
    {
      "id": 20281442729,
      "name": ".github/workflows/hardening-gate.yml",
      "event": "push",
      "status": "completed",
      "conclusion": "failure",
      "created_at": "2025-12-16T20:16:26Z",
      "updated_at": "2025-12-16T20:16:26Z",
      "duration_ms": 0
    },
    {
      "id": 20281442451,
      "name": ".github/workflows/ltdd-sync-branch-protection.yml",
      "event": "push",
      "status": "completed",
      "conclusion": "failure",
      "created_at": "2025-12-16T20:16:25Z",
      "updated_at": "2025-12-16T20:16:25Z",
      "duration_ms": 0
    },
    {
      "id": 20280156014,
      "name": ".github/workflows/ltdd-sync-branch-protection.yml",
      "event": "push",
      "status": "completed",
      "conclusion": "failure",
      "created_at": "2025-12-16T19:27:41Z",
      "updated_at": "2025-12-16T19:27:41Z",
      "duration_ms": 0
    },
    {
      "id": 20280156326,
      "name": "Prod Guardrails",
      "event": "push",
      "status": "completed",
      "conclusion": "failure",
      "created_at": "2025-12-16T19:27:41Z",
      "updated_at": "2025-12-16T19:28:26Z",
      "duration_ms": 45000
    },
    {
      "id": 20280156332,
      "name": "Lock Tests (Production Sentinel)",
      "event": "push",
      "status": "completed",
      "conclusion": "failure",
      "created_at": "2025-12-16T19:27:41Z",
      "updated_at": "2025-12-16T19:30:14Z",
      "duration_ms": 153000
    },
    {
      "id": 20280156348,
      "name": "Release (Golden Path)",
      "event": "push",
      "status": "completed",
      "conclusion": "success",
      "created_at": "2025-12-16T19:27:41Z",
      "updated_at": "2025-12-16T19:37:51Z",
      "duration_ms": 610000
    },
    {
      "id": 20280155627,
      "name": ".github/workflows/ci.yml",
      "event": "push",
      "status": "completed",
      "conclusion": "failure",
      "created_at": "2025-12-16T19:27:40Z",
      "updated_at": "2025-12-16T19:27:40Z",
      "duration_ms": 0
    },
    {
      "id": 20280155817,
      "name": ".github/workflows/daily-ltdd-telemetry.yml",
      "event": "push",
      "status": "completed",
      "conclusion": "failure",
      "created_at": "2025-12-16T19:27:40Z",
      "updated_at": "2025-12-16T19:27:40Z",
      "duration_ms": 0
    },
    {
      "id": 20280155469,
      "name": ".github/workflows/hardening-gate.yml",
      "event": "push",
      "status": "completed",
      "conclusion": "failure",
      "created_at": "2025-12-16T19:27:39Z",
      "updated_at": "2025-12-16T19:27:39Z",
      "duration_ms": 0
    },
    {
      "id": 20279985805,
      "name": "Ping (Actions Test)",
      "event": "push",
      "status": "completed",
      "conclusion": "success",
      "created_at": "2025-12-16T19:21:28Z",
      "updated_at": "2025-12-16T19:21:35Z",
      "duration_ms": 7000
    },
    {
      "id": 20279985135,
      "name": ".github/workflows/ltdd-sync-branch-protection.yml",
      "event": "push",
      "status": "completed",
      "conclusion": "failure",
      "created_at": "2025-12-16T19:21:27Z",
      "updated_at": "2025-12-16T19:21:27Z",
      "duration_ms": 0
    },
    {
      "id": 20279985307,
      "name": ".github/workflows/ci.yml",
      "event": "push",
      "status": "completed",
      "conclusion": "failure",
      "created_at": "2025-12-16T19:21:27Z",
      "updated_at": "2025-12-16T19:21:27Z",
      "duration_ms": 0
    },
    {
      "id": 20279984794,
      "name": ".github/workflows/daily-ltdd-telemetry.yml",
      "event": "push",
      "status": "completed",
      "conclusion": "failure",
      "created_at": "2025-12-16T19:21:26Z",
      "updated_at": "2025-12-16T19:21:26Z",
      "duration_ms": 0
    },
    {
      "id": 20279984970,
      "name": ".github/workflows/hardening-gate.yml",
      "event": "push",
      "status": "completed",
      "conclusion": "failure",
      "created_at": "2025-12-16T19:21:26Z",
      "updated_at": "2025-12-16T19:21:26Z",
      "duration_ms": 0
    },
    {
      "id": 20279931829,
      "name": ".github/workflows/hardening-gate.yml",
      "event": "push",
      "status": "completed",
      "conclusion": "failure",
      "created_at": "2025-12-16T19:19:33Z",
      "updated_at": "2025-12-16T19:19:33Z",
      "duration_ms": 0
    },
    {
      "id": 20279931952,
      "name": ".github/workflows/daily-ltdd-telemetry.yml",
      "event": "push",
      "status": "completed",
      "conclusion": "failure",
      "created_at": "2025-12-16T19:19:33Z",
      "updated_at": "2025-12-16T19:19:33Z",
      "duration_ms": 0
    },
    {
      "id": 20279932090,
      "name": ".github/workflows/ci.yml",
      "event": "push",
      "status": "completed",
      "conclusion": "failure",
      "created_at": "2025-12-16T19:19:33Z",
      "updated_at": "2025-12-16T19:19:33Z",
      "duration_ms": 0
    },
    {
      "id": 20279931711,
      "name": ".github/workflows/ltdd-sync-branch-protection.yml",
      "event": "push",
      "status": "completed",
      "conclusion": "failure",
      "created_at": "2025-12-16T19:19:32Z",
      "updated_at": "2025-12-16T19:19:32Z",
      "duration_ms": 0
    },
    {
      "id": 20278941007,
      "name": "Release (Golden Path)",
      "event": "push",
      "status": "completed",
      "conclusion": "success",
      "created_at": "2025-12-16T18:42:44Z",
      "updated_at": "2025-12-16T18:52:45Z",
      "duration_ms": 601000
    },
    {
      "id": 20278940712,
      "name": ".github/workflows/ci.yml",
      "event": "push",
      "status": "completed",
      "conclusion": "failure",
      "created_at": "2025-12-16T18:42:43Z",
      "updated_at": "2025-12-16T18:42:43Z",
      "duration_ms": 0
    },
    {
      "id": 20278940974,
      "name": "Prod Guardrails",
      "event": "push",
      "status": "completed",
      "conclusion": "failure",
      "created_at": "2025-12-16T18:42:43Z",
      "updated_at": "2025-12-16T18:43:28Z",
      "duration_ms": 45000
    },
    {
      "id": 20278940995,
      "name": "Lock Tests (Production Sentinel)",
      "event": "push",
      "status": "completed",
      "conclusion": "failure",
      "created_at": "2025-12-16T18:42:43Z",
      "updated_at": "2025-12-16T18:45:18Z",
      "duration_ms": 155000
    },
    {
      "id": 20278940318,
      "name": ".github/workflows/hardening-gate.yml",
      "event": "push",
      "status": "completed",
      "conclusion": "failure",
      "created_at": "2025-12-16T18:42:42Z",
      "updated_at": "2025-12-16T18:42:42Z",
      "duration_ms": 0
    },
    {
      "id": 20278940564,
      "name": ".github/workflows/daily-ltdd-telemetry.yml",
      "event": "push",
      "status": "completed",
      "conclusion": "failure",
      "created_at": "2025-12-16T18:42:42Z",
      "updated_at": "2025-12-16T18:42:42Z",
      "duration_ms": 0
    },
    {
      "id": 20278940183,
      "name": ".github/workflows/ltdd-sync-branch-protection.yml",
      "event": "push",
      "status": "completed",
      "conclusion": "failure",
      "created_at": "2025-12-16T18:42:42Z",
      "updated_at": "2025-12-16T18:42:42Z",
      "duration_ms": 0
    },
    {
      "id": 20278752670,
      "name": ".github/workflows/daily-ltdd-telemetry.yml",
      "event": "push",
      "status": "completed",
      "conclusion": "failure",
      "created_at": "2025-12-16T18:35:36Z",
      "updated_at": "2025-12-16T18:35:36Z",
      "duration_ms": 0
    },
    {
      "id": 20278752244,
      "name": ".github/workflows/ltdd-sync-branch-protection.yml",
      "event": "push",
      "status": "completed",
      "conclusion": "failure",
      "created_at": "2025-12-16T18:35:35Z",
      "updated_at": "2025-12-16T18:35:35Z",
      "duration_ms": 0
    },
    {
      "id": 20278752379,
      "name": ".github/workflows/hardening-gate.yml",
      "event": "push",
      "status": "completed",
      "conclusion": "failure",
      "created_at": "2025-12-16T18:35:35Z",
      "updated_at": "2025-12-16T18:35:35Z",
      "duration_ms": 0
    },
    {
      "id": 20278752517,
      "name": ".github/workflows/ci.yml",
      "event": "push",
      "status": "completed",
      "conclusion": "failure",
      "created_at": "2025-12-16T18:35:35Z",
      "updated_at": "2025-12-16T18:35:35Z",
      "duration_ms": 0
    },
    {
      "id": 20278717972,
      "name": ".github/workflows/ci.yml",
      "event": "push",
      "status": "completed",
      "conclusion": "failure",
      "created_at": "2025-12-16T18:34:16Z",
      "updated_at": "2025-12-16T18:34:16Z",
      "duration_ms": 0
    },
    {
      "id": 20278717733,
      "name": ".github/workflows/daily-ltdd-telemetry.yml",
      "event": "push",
      "status": "completed",
      "conclusion": "failure",
      "created_at": "2025-12-16T18:34:15Z",
      "updated_at": "2025-12-16T18:34:15Z",
      "duration_ms": 0
    },
    {
      "id": 20278717494,
      "name": ".github/workflows/ltdd-sync-branch-protection.yml",
      "event": "push",
      "status": "completed",
      "conclusion": "failure",
      "created_at": "2025-12-16T18:34:14Z",
      "updated_at": "2025-12-16T18:34:14Z",
      "duration_ms": 0
    },
    {
      "id": 20278717294,
      "name": ".github/workflows/hardening-gate.yml",
      "event": "push",
      "status": "completed",
      "conclusion": "failure",
      "created_at": "2025-12-16T18:34:14Z",
      "updated_at": "2025-12-16T18:34:14Z",
      "duration_ms": 0
    },
    {
      "id": 20278458227,
      "name": "Prod Guardrails",
      "event": "push",
      "status": "completed",
      "conclusion": "failure",
      "created_at": "2025-12-16T18:24:34Z",
      "updated_at": "2025-12-16T18:25:14Z",
      "duration_ms": 40000
    },
    {
      "id": 20278458230,
      "name": "Release (Golden Path)",
      "event": "push",
      "status": "completed",
      "conclusion": "failure",
      "created_at": "2025-12-16T18:24:34Z",
      "updated_at": "2025-12-16T18:25:27Z",
      "duration_ms": 53000
    },
    {
      "id": 20278458209,
      "name": "Lock Tests (Production Sentinel)",
      "event": "push",
      "status": "completed",
      "conclusion": "failure",
      "created_at": "2025-12-16T18:24:34Z",
      "updated_at": "2025-12-16T18:27:12Z",
      "duration_ms": 158000
    },
    {
      "id": 20278457602,
      "name": ".github/workflows/ci.yml",
      "event": "push",
      "status": "completed",
      "conclusion": "failure",
      "created_at": "2025-12-16T18:24:33Z",
      "updated_at": "2025-12-16T18:24:33Z",
      "duration_ms": 0
    },
    {
      "id": 20278457784,
      "name": ".github/workflows/hardening-gate.yml",
      "event": "push",
      "status": "completed",
      "conclusion": "failure",
      "created_at": "2025-12-16T18:24:33Z",
      "updated_at": "2025-12-16T18:24:33Z",
      "duration_ms": 0
    },
    {
      "id": 20278457150,
      "name": ".github/workflows/daily-ltdd-telemetry.yml",
      "event": "push",
      "status": "completed",
      "conclusion": "failure",
      "created_at": "2025-12-16T18:24:32Z",
      "updated_at": "2025-12-16T18:24:32Z",
      "duration_ms": 0
    },
    {
      "id": 20278457383,
      "name": ".github/workflows/ltdd-sync-branch-protection.yml",
      "event": "push",
      "status": "completed",
      "conclusion": "failure",
      "created_at": "2025-12-16T18:24:32Z",
      "updated_at": "2025-12-16T18:24:32Z",
      "duration_ms": 0
    }
  ]
}
