{
  "since": "2025-11-14T03:31:17Z",
  "total_runs": 132,
  "runs": [
    {
      "id": 19383649658,
      "name": ".github/workflows/daily-ltdd-telemetry.yml",
      "event": "push",
      "status": "completed",
      "conclusion": "failure",
      "created_at": "2025-11-15T03:21:20Z",
      "updated_at": "2025-11-15T03:21:20Z",
      "duration_ms": 0
    },
    {
      "id": 19383649698,
      "name": ".github/workflows/ci.yml",
      "event": "push",
      "status": "completed",
      "conclusion": "failure",
      "created_at": "2025-11-15T03:21:20Z",
      "updated_at": "2025-11-15T03:21:20Z",
      "duration_ms": 0
    },
    {
      "id": 19383649763,
      "name": "Verify Complete LTDD Hardening",
      "event": "push",
      "status": "completed",
      "conclusion": "failure",
      "created_at": "2025-11-15T03:21:20Z",
      "updated_at": "2025-11-15T03:21:34Z",
      "duration_ms": 14000
    },
    {
      "id": 19383649775,
      "name": "Prod Guardrails",
      "event": "push",
      "status": "completed",
      "conclusion": "failure",
      "created_at": "2025-11-15T03:21:20Z",
      "updated_at": "2025-11-15T03:21:56Z",
      "duration_ms": 36000
    },
    {
      "id": 19383649769,
      "name": "Lock Tests (Production Sentinel)",
      "event": "push",
      "status": "completed",
      "conclusion": "failure",
      "created_at": "2025-11-15T03:21:20Z",
      "updated_at": "2025-11-15T03:22:28Z",
      "duration_ms": 68000
    },
    {
      "id": 19383649770,
      "name": "Release (Golden Path)",
      "event": "push",
      "status": "completed",
      "conclusion": "failure",
      "created_at": "2025-11-15T03:21:20Z",
      "updated_at": "2025-11-15T03:25:04Z",
      "duration_ms": 224000
    },
    {
      "id": 19383230634,
      "name": ".github/workflows/ci.yml",
      "event": "push",
      "status": "completed",
      "conclusion": "failure",
      "created_at": "2025-11-15T02:45:57Z",
      "updated_at": "2025-11-15T02:45:57Z",
      "duration_ms": 0
    },
    {
      "id": 19383230564,
      "name": ".github/workflows/daily-ltdd-telemetry.yml",
      "event": "push",
      "status": "completed",
      "conclusion": "failure",
      "created_at": "2025-11-15T02:45:56Z",
      "updated_at": "2025-11-15T02:45:56Z",
      "duration_ms": 0
    },
    {
      "id": 19382718080,
      "name": ".github/workflows/ci.yml",
      "event": "push",
      "status": "completed",
      "conclusion": "failure",
      "created_at": "2025-11-15T02:04:00Z",
      "updated_at": "2025-11-15T02:04:00Z",
      "duration_ms": 0
    },
    {
      "id": 19382718190,
      "name": "Verify Complete LTDD Hardening",
      "event": "push",
      "status": "completed",
      "conclusion": "failure",
      "created_at": "2025-11-15T02:04:00Z",
      "updated_at": "2025-11-15T02:04:14Z",
      "duration_ms": 14000
    },
    {
      "id": 19382718182,
      "name": "Prod Guardrails",
      "event": "push",
      "status": "completed",
      "conclusion": "failure",
      "created_at": "2025-11-15T02:04:00Z",
      "updated_at": "2025-11-15T02:04:39Z",
      "duration_ms": 39000
    },
    {
      "id": 19382718191,
      "name": "Lock Tests (Production Sentinel)",
      "event": "push",
      "status": "completed",
      "conclusion": "failure",
      "created_at": "2025-11-15T02:04:00Z",
      "updated_at": "2025-11-15T02:05:09Z",
      "duration_ms": 69000
    },
    {
      "id": 19382718189,
      "name": "Release (Golden Path)",
      "event": "push",
      "status": "completed",
      "conclusion": "failure",
      "created_at": "2025-11-15T02:04:00Z",
      "updated_at": "2025-11-15T02:07:43Z",
      "duration_ms": 223000
    },
    {
      "id": 19382718001,
      "name": ".github/workflows/daily-ltdd-telemetry.yml",
      "event": "push",
      "status": "completed",
      "conclusion": "failure",
      "created_at": "2025-11-15T02:03:59Z",
      "updated_at": "2025-11-15T02:03:59Z",
      "duration_ms": 0
    },
    {
      "id": 19382666682,
      "name": ".github/workflows/daily-ltdd-telemetry.yml",
      "event": "push",
      "status": "completed",
      "conclusion": "failure",
      "created_at": "2025-11-15T01:59:46Z",
      "updated_at": "2025-11-15T01:59:46Z",
      "duration_ms": 0
    },
    {
      "id": 19382666754,
      "name": ".github/workflows/ci.yml",
      "event": "push",
      "status": "completed",
      "conclusion": "failure",
      "created_at": "2025-11-15T01:59:46Z",
      "updated_at": "2025-11-15T01:59:46Z",
      "duration_ms": 0
    },
    {
      "id": 19382290679,
      "name": "Verify Complete LTDD Hardening",
      "event": "push",
      "status": "completed",
      "conclusion": "failure",
      "created_at": "2025-11-15T01:31:19Z",
      "updated_at": "2025-11-15T01:31:31Z",
      "duration_ms": 12000
    },
    {
      "id": 19382290568,
      "name": ".github/workflows/ci.yml",
      "event": "push",
      "status": "completed",
      "conclusion": "failure",
      "created_at": "2025-11-15T01:31:19Z",
      "updated_at": "2025-11-15T01:31:19Z",
      "duration_ms": 0
    },
    {
      "id": 19382290659,
      "name": "Prod Guardrails",
      "event": "push",
      "status": "completed",
      "conclusion": "failure",
      "created_at": "2025-11-15T01:31:19Z",
      "updated_at": "2025-11-15T01:31:53Z",
      "duration_ms": 34000
    },
    {
      "id": 19382290660,
      "name": "Lock Tests (Production Sentinel)",
      "event": "push",
      "status": "completed",
      "conclusion": "failure",
      "created_at": "2025-11-15T01:31:19Z",
      "updated_at": "2025-11-15T01:32:32Z",
      "duration_ms": 73000
    },
    {
      "id": 19382290651,
      "name": "Release (Golden Path)",
      "event": "push",
      "status": "completed",
      "conclusion": "failure",
      "created_at": "2025-11-15T01:31:19Z",
      "updated_at": "2025-11-15T01:35:05Z",
      "duration_ms": 226000
    },
    {
      "id": 19382290509,
      "name": ".github/workflows/daily-ltdd-telemetry.yml",
      "event": "push",
      "status": "completed",
      "conclusion": "failure",
      "created_at": "2025-11-15T01:31:18Z",
      "updated_at": "2025-11-15T01:31:18Z",
      "duration_ms": 0
    },
    {
      "id": 19382208937,
      "name": ".github/workflows/daily-ltdd-telemetry.yml",
      "event": "push",
      "status": "completed",
      "conclusion": "failure",
      "created_at": "2025-11-15T01:25:22Z",
      "updated_at": "2025-11-15T01:25:22Z",
      "duration_ms": 0
    },
    {
      "id": 19382208992,
      "name": ".github/workflows/ci.yml",
      "event": "push",
      "status": "completed",
      "conclusion": "failure",
      "created_at": "2025-11-15T01:25:22Z",
      "updated_at": "2025-11-15T01:25:22Z",
      "duration_ms": 0
    },
    {
      "id": 19381894920,
      "name": "Lock Tests (Production Sentinel)",
      "event": "push",
      "status": "completed",
      "conclusion": "failure",
      "created_at": "2025-11-15T01:02:35Z",
      "updated_at": "2025-11-15T01:03:45Z",
      "duration_ms": 70000
    },
    {
      "id": 19381894914,
      "name": "Prod Guardrails",
      "event": "push",
      "status": "completed",
      "conclusion": "failure",
      "created_at": "2025-11-15T01:02:34Z",
      "updated_at": "2025-11-15T01:03:12Z",
      "duration_ms": 38000
    },
    {
      "id": 19381894902,
      "name": "Verify Complete LTDD Hardening",
      "event": "push",
      "status": "completed",
      "conclusion": "failure",
      "created_at": "2025-11-15T01:02:34Z",
      "updated_at": "2025-11-15T01:02:47Z",
      "duration_ms": 13000
    },
    {
      "id": 19381894913,
      "name": "Release (Golden Path)",
      "event": "push",
      "status": "completed",
      "conclusion": "failure",
      "created_at": "2025-11-15T01:02:34Z",
      "updated_at": "2025-11-15T01:06:18Z",
      "duration_ms": 224000
    },
    {
      "id": 19381894718,
      "name": ".github/workflows/daily-ltdd-telemetry.yml",
      "event": "push",
      "status": "completed",
      "conclusion": "failure",
      "created_at": "2025-11-15T01:02:34Z",
      "updated_at": "2025-11-15T01:02:34Z",
      "duration_ms": 0
    },
    {
      "id": 19381894787,
      "name": ".github/workflows/ci.yml",
      "event": "push",
      "status": "completed",
      "conclusion": "failure",
      "created_at": "2025-11-15T01:02:34Z",
      "updated_at": "2025-11-15T01:02:34Z",
      "duration_ms": 0
    },
    {
      "id": 19381823314,
      "name": ".github/workflows/ci.yml",
      "event": "push",
      "status": "completed",
      "conclusion": "failure",
      "created_at": "2025-11-15T00:58:05Z",
      "updated_at": "2025-11-15T00:58:05Z",
      "duration_ms": 0
    },
    {
      "id": 19381823235,
      "name": ".github/workflows/daily-ltdd-telemetry.yml",
      "event": "push",
      "status": "completed",
      "conclusion": "failure",
      "created_at": "2025-11-15T00:58:04Z",
      "updated_at": "2025-11-15T00:58:04Z",
      "duration_ms": 0
    },
    {
      "id": 19381464952,
      "name": "Verify Complete LTDD Hardening",
      "event": "push",
      "status": "completed",
      "conclusion": "failure",
      "created_at": "2025-11-15T00:33:37Z",
      "updated_at": "2025-11-15T00:33:48Z",
      "duration_ms": 11000
    },
    {
      "id": 19381464869,
      "name": ".github/workflows/ci.yml",
      "event": "push",
      "status": "completed",
      "conclusion": "failure",
      "created_at": "2025-11-15T00:33:37Z",
      "updated_at": "2025-11-15T00:33:37Z",
      "duration_ms": 0
    },
    {
      "id": 19381464966,
      "name": "Prod Guardrails",
      "event": "push",
      "status": "completed",
      "conclusion": "failure",
      "created_at": "2025-11-15T00:33:37Z",
      "updated_at": "2025-11-15T00:34:16Z",
      "duration_ms": 39000
    },
    {
      "id": 19381464959,
      "name": "Lock Tests (Production Sentinel)",
      "event": "push",
      "status": "completed",
      "conclusion": "failure",
      "created_at": "2025-11-15T00:33:37Z",
      "updated_at": "2025-11-15T00:34:51Z",
      "duration_ms": 74000
    },
    {
      "id": 19381464960,
      "name": "Release (Golden Path)",
      "event": "push",
      "status": "completed",
      "conclusion": "failure",
      "created_at": "2025-11-15T00:33:37Z",
      "updated_at": "2025-11-15T00:37:30Z",
      "duration_ms": 233000
    },
    {
      "id": 19381464814,
      "name": ".github/workflows/daily-ltdd-telemetry.yml",
      "event": "push",
      "status": "completed",
      "conclusion": "failure",
      "created_at": "2025-11-15T00:33:36Z",
      "updated_at": "2025-11-15T00:33:36Z",
      "duration_ms": 0
    },
    {
      "id": 19381325062,
      "name": ".github/workflows/daily-ltdd-telemetry.yml",
      "event": "push",
      "status": "completed",
      "conclusion": "failure",
      "created_at": "2025-11-15T00:25:00Z",
      "updated_at": "2025-11-15T00:25:00Z",
      "duration_ms": 0
    },
    {
      "id": 19381325136,
      "name": ".github/workflows/ci.yml",
      "event": "push",
      "status": "completed",
      "conclusion": "failure",
      "created_at": "2025-11-15T00:25:00Z",
      "updated_at": "2025-11-15T00:25:00Z",
      "duration_ms": 0
    },
    {
      "id": 19381160983,
      "name": "Verify Complete LTDD Hardening",
      "event": "push",
      "status": "completed",
      "conclusion": "failure",
      "created_at": "2025-11-15T00:14:39Z",
      "updated_at": "2025-11-15T00:14:49Z",
      "duration_ms": 10000
    },
    {
      "id": 19381160975,
      "name": "Prod Guardrails",
      "event": "push",
      "status": "completed",
      "conclusion": "failure",
      "created_at": "2025-11-15T00:14:39Z",
      "updated_at": "2025-11-15T00:15:21Z",
      "duration_ms": 42000
    },
    {
      "id": 19381160993,
      "name": "Lock Tests (Production Sentinel)",
      "event": "push",
      "status": "completed",
      "conclusion": "failure",
      "created_at": "2025-11-15T00:14:39Z",
      "updated_at": "2025-11-15T00:15:48Z",
      "duration_ms": 69000
    },
    {
      "id": 19381160974,
      "name": "Release (Golden Path)",
      "event": "push",
      "status": "completed",
      "conclusion": "failure",
      "created_at": "2025-11-15T00:14:39Z",
      "updated_at": "2025-11-15T00:18:35Z",
      "duration_ms": 236000
    },
    {
      "id": 19381160709,
      "name": ".github/workflows/ci.yml",
      "event": "push",
      "status": "completed",
      "conclusion": "failure",
      "created_at": "2025-11-15T00:14:38Z",
      "updated_at": "2025-11-15T00:14:38Z",
      "duration_ms": 0
    },
    {
      "id": 19381160807,
      "name": ".github/workflows/daily-ltdd-telemetry.yml",
      "event": "push",
      "status": "completed",
      "conclusion": "failure",
      "created_at": "2025-11-15T00:14:38Z",
      "updated_at": "2025-11-15T00:14:38Z",
      "duration_ms": 0
    },
    {
      "id": 19380975407,
      "name": ".github/workflows/daily-ltdd-telemetry.yml",
      "event": "push",
      "status": "completed",
      "conclusion": "failure",
      "created_at": "2025-11-15T00:03:06Z",
      "updated_at": "2025-11-15T00:03:06Z",
      "duration_ms": 0
    },
    {
      "id": 19380975434,
      "name": ".github/workflows/ci.yml",
      "event": "push",
      "status": "completed",
      "conclusion": "failure",
      "created_at": "2025-11-15T00:03:06Z",
      "updated_at": "2025-11-15T00:03:06Z",
      "duration_ms": 0
    },
    {
      "id": 19380834743,
      "name": "Verify Complete LTDD Hardening",
      "event": "push",
      "status": "completed",
      "conclusion": "failure",
      "created_at": "2025-11-14T23:52:47Z",
      "updated_at": "2025-11-14T23:53:00Z",
      "duration_ms": 13000
    },
    {
      "id": 19380834745,
      "name": "Prod Guardrails",
      "event": "push",
      "status": "completed",
      "conclusion": "failure",
      "created_at": "2025-11-14T23:52:47Z",
      "updated_at": "2025-11-14T23:53:21Z",
      "duration_ms": 34000
    },
    {
      "id": 19380834750,
      "name": "Lock Tests (Production Sentinel)",
      "event": "push",
      "status": "completed",
      "conclusion": "failure",
      "created_at": "2025-11-14T23:52:47Z",
      "updated_at": "2025-11-14T23:54:13Z",
      "duration_ms": 86000
    },
    {
      "id": 19380834755,
      "name": "Release (Golden Path)",
      "event": "push",
      "status": "completed",
      "conclusion": "failure",
      "created_at": "2025-11-14T23:52:47Z",
      "updated_at": "2025-11-14T23:56:33Z",
      "duration_ms": 226000
    },
    {
      "id": 19380834472,
      "name": ".github/workflows/daily-ltdd-telemetry.yml",
      "event": "push",
      "status": "completed",
      "conclusion": "failure",
      "created_at": "2025-11-14T23:52:46Z",
      "updated_at": "2025-11-14T23:52:46Z",
      "duration_ms": 0
    },
    {
      "id": 19380834534,
      "name": ".github/workflows/ci.yml",
      "event": "push",
      "status": "completed",
      "conclusion": "failure",
      "created_at": "2025-11-14T23:52:46Z",
      "updated_at": "2025-11-14T23:52:46Z",
      "duration_ms": 0
    },
    {
      "id": 19380669415,
      "name": ".github/workflows/ci.yml",
      "event": "push",
      "status": "completed",
      "conclusion": "failure",
      "created_at": "2025-11-14T23:41:34Z",
      "updated_at": "2025-11-14T23:41:34Z",
      "duration_ms": 0
    },
    {
      "id": 19380669306,
      "name": ".github/workflows/daily-ltdd-telemetry.yml",
      "event": "push",
      "status": "completed",
      "conclusion": "failure",
      "created_at": "2025-11-14T23:41:33Z",
      "updated_at": "2025-11-14T23:41:33Z",
      "duration_ms": 0
    },
    {
      "id": 19380600933,
      "name": "Verify Complete LTDD Hardening",
      "event": "push",
      "status": "completed",
      "conclusion": "failure",
      "created_at": "2025-11-14T23:37:11Z",
      "updated_at": "2025-11-14T23:37:23Z",
      "duration_ms": 12000
    },
    {
      "id": 19380600930,
      "name": "Prod Guardrails",
      "event": "push",
      "status": "completed",
      "conclusion": "failure",
      "created_at": "2025-11-14T23:37:11Z",
      "updated_at": "2025-11-14T23:37:43Z",
      "duration_ms": 32000
    },
    {
      "id": 19380600921,
      "name": "Lock Tests (Production Sentinel)",
      "event": "push",
      "status": "completed",
      "conclusion": "failure",
      "created_at": "2025-11-14T23:37:11Z",
      "updated_at": "2025-11-14T23:38:19Z",
      "duration_ms": 68000
    },
    {
      "id": 19380600934,
      "name": "Release (Golden Path)",
      "event": "push",
      "status": "completed",
      "conclusion": "failure",
      "created_at": "2025-11-14T23:37:11Z",
      "updated_at": "2025-11-14T23:40:55Z",
      "duration_ms": 224000
    },
    {
      "id": 19380600666,
      "name": ".github/workflows/ci.yml",
      "event": "push",
      "status": "completed",
      "conclusion": "failure",
      "created_at": "2025-11-14T23:37:10Z",
      "updated_at": "2025-11-14T23:37:10Z",
      "duration_ms": 0
    },
    {
      "id": 19380600765,
      "name": ".github/workflows/daily-ltdd-telemetry.yml",
      "event": "push",
      "status": "completed",
      "conclusion": "failure",
      "created_at": "2025-11-14T23:37:10Z",
      "updated_at": "2025-11-14T23:37:10Z",
      "duration_ms": 0
    },
    {
      "id": 19380461292,
      "name": ".github/workflows/daily-ltdd-telemetry.yml",
      "event": "push",
      "status": "completed",
      "conclusion": "failure",
      "created_at": "2025-11-14T23:29:03Z",
      "updated_at": "2025-11-14T23:29:03Z",
      "duration_ms": 0
    },
    {
      "id": 19380461462,
      "name": ".github/workflows/ci.yml",
      "event": "push",
      "status": "completed",
      "conclusion": "failure",
      "created_at": "2025-11-14T23:29:03Z",
      "updated_at": "2025-11-14T23:29:03Z",
      "duration_ms": 0
    },
    {
      "id": 19377708701,
      "name": "Verify Complete LTDD Hardening",
      "event": "push",
      "status": "completed",
      "conclusion": "failure",
      "created_at": "2025-11-14T21:11:02Z",
      "updated_at": "2025-11-14T21:11:12Z",
      "duration_ms": 10000
    },
    {
      "id": 19377708694,
      "name": "Prod Guardrails",
      "event": "push",
      "status": "completed",
      "conclusion": "failure",
      "created_at": "2025-11-14T21:11:02Z",
      "updated_at": "2025-11-14T21:11:42Z",
      "duration_ms": 40000
    },
    {
      "id": 19377708737,
      "name": "Lock Tests (Production Sentinel)",
      "event": "push",
      "status": "completed",
      "conclusion": "failure",
      "created_at": "2025-11-14T21:11:02Z",
      "updated_at": "2025-11-14T21:12:26Z",
      "duration_ms": 84000
    },
    {
      "id": 19377708714,
      "name": "Release (Golden Path)",
      "event": "push",
      "status": "completed",
      "conclusion": "failure",
      "created_at": "2025-11-14T21:11:02Z",
      "updated_at": "2025-11-14T21:14:53Z",
      "duration_ms": 231000
    },
    {
      "id": 19377708356,
      "name": ".github/workflows/daily-ltdd-telemetry.yml",
      "event": "push",
      "status": "completed",
      "conclusion": "failure",
      "created_at": "2025-11-14T21:11:01Z",
      "updated_at": "2025-11-14T21:11:01Z",
      "duration_ms": 0
    },
    {
      "id": 19377708471,
      "name": ".github/workflows/ci.yml",
      "event": "push",
      "status": "completed",
      "conclusion": "failure",
      "created_at": "2025-11-14T21:11:01Z",
      "updated_at": "2025-11-14T21:11:01Z",
      "duration_ms": 0
    },
    {
      "id": 19377610072,
      "name": ".github/workflows/daily-ltdd-telemetry.yml",
      "event": "push",
      "status": "completed",
      "conclusion": "failure",
      "created_at": "2025-11-14T21:06:37Z",
      "updated_at": "2025-11-14T21:06:37Z",
      "duration_ms": 0
    },
    {
      "id": 19377609893,
      "name": ".github/workflows/ci.yml",
      "event": "push",
      "status": "completed",
      "conclusion": "failure",
      "created_at": "2025-11-14T21:06:37Z",
      "updated_at": "2025-11-14T21:06:37Z",
      "duration_ms": 0
    },
    {
      "id": 19377121306,
      "name": "Verify Complete LTDD Hardening",
      "event": "push",
      "status": "completed",
      "conclusion": "failure",
      "created_at": "2025-11-14T20:44:10Z",
      "updated_at": "2025-11-14T20:44:21Z",
      "duration_ms": 11000
    },
    {
      "id": 19377121301,
      "name": "Prod Guardrails",
      "event": "push",
      "status": "completed",
      "conclusion": "failure",
      "created_at": "2025-11-14T20:44:10Z",
      "updated_at": "2025-11-14T20:44:48Z",
      "duration_ms": 38000
    },
    {
      "id": 19377121325,
      "name": "Lock Tests (Production Sentinel)",
      "event": "push",
      "status": "completed",
      "conclusion": "failure",
      "created_at": "2025-11-14T20:44:10Z",
      "updated_at": "2025-11-14T20:45:14Z",
      "duration_ms": 64000
    },
    {
      "id": 19377121309,
      "name": "Release (Golden Path)",
      "event": "push",
      "status": "completed",
      "conclusion": "failure",
      "created_at": "2025-11-14T20:44:10Z",
      "updated_at": "2025-11-14T20:47:51Z",
      "duration_ms": 221000
    },
    {
      "id": 19377120955,
      "name": ".github/workflows/daily-ltdd-telemetry.yml",
      "event": "push",
      "status": "completed",
      "conclusion": "failure",
      "created_at": "2025-11-14T20:44:09Z",
      "updated_at": "2025-11-14T20:44:09Z",
      "duration_ms": 0
    },
    {
      "id": 19377121063,
      "name": ".github/workflows/ci.yml",
      "event": "push",
      "status": "completed",
      "conclusion": "failure",
      "created_at": "2025-11-14T20:44:09Z",
      "updated_at": "2025-11-14T20:44:09Z",
      "duration_ms": 0
    },
    {
      "id": 19377004387,
      "name": ".github/workflows/daily-ltdd-telemetry.yml",
      "event": "push",
      "status": "completed",
      "conclusion": "failure",
      "created_at": "2025-11-14T20:38:53Z",
      "updated_at": "2025-11-14T20:38:53Z",
      "duration_ms": 0
    },
    {
      "id": 19377004500,
      "name": ".github/workflows/ci.yml",
      "event": "push",
      "status": "completed",
      "conclusion": "failure",
      "created_at": "2025-11-14T20:38:53Z",
      "updated_at": "2025-11-14T20:38:53Z",
      "duration_ms": 0
    },
    {
      "id": 19376656771,
      "name": ".github/workflows/daily-ltdd-telemetry.yml",
      "event": "push",
      "status": "completed",
      "conclusion": "failure",
      "created_at": "2025-11-14T20:23:34Z",
      "updated_at": "2025-11-14T20:23:34Z",
      "duration_ms": 0
    },
    {
      "id": 19376656626,
      "name": ".github/workflows/ci.yml",
      "event": "push",
      "status": "completed",
      "conclusion": "failure",
      "created_at": "2025-11-14T20:23:33Z",
      "updated_at": "2025-11-14T20:23:33Z",
      "duration_ms": 0
    },
    {
      "id": 19375548413,
      "name": ".github/workflows/daily-ltdd-telemetry.yml",
      "event": "push",
      "status": "completed",
      "conclusion": "failure",
      "created_at": "2025-11-14T19:34:26Z",
      "updated_at": "2025-11-14T19:34:26Z",
      "duration_ms": 0
    },
    {
      "id": 19375548521,
      "name": ".github/workflows/ci.yml",
      "event": "push",
      "status": "completed",
      "conclusion": "failure",
      "created_at": "2025-11-14T19:34:26Z",
      "updated_at": "2025-11-14T19:34:26Z",
      "duration_ms": 0
    },
    {
      "id": 19375325177,
      "name": "Verify Complete LTDD Hardening",
      "event": "push",
      "status": "completed",
      "conclusion": "failure",
      "created_at": "2025-11-14T19:25:09Z",
      "updated_at": "2025-11-14T19:25:19Z",
      "duration_ms": 10000
    },
    {
      "id": 19375325181,
      "name": "Prod Guardrails",
      "event": "push",
      "status": "completed",
      "conclusion": "failure",
      "created_at": "2025-11-14T19:25:09Z",
      "updated_at": "2025-11-14T19:25:52Z",
      "duration_ms": 43000
    },
    {
      "id": 19375325188,
      "name": "Lock Tests (Production Sentinel)",
      "event": "push",
      "status": "completed",
      "conclusion": "failure",
      "created_at": "2025-11-14T19:25:09Z",
      "updated_at": "2025-11-14T19:26:28Z",
      "duration_ms": 79000
    },
    {
      "id": 19375325197,
      "name": "Release (Golden Path)",
      "event": "push",
      "status": "completed",
      "conclusion": "failure",
      "created_at": "2025-11-14T19:25:09Z",
      "updated_at": "2025-11-14T19:29:03Z",
      "duration_ms": 234000
    },
    {
      "id": 19375324598,
      "name": ".github/workflows/daily-ltdd-telemetry.yml",
      "event": "push",
      "status": "completed",
      "conclusion": "failure",
      "created_at": "2025-11-14T19:25:08Z",
      "updated_at": "2025-11-14T19:25:08Z",
      "duration_ms": 0
    },
    {
      "id": 19375324869,
      "name": ".github/workflows/ci.yml",
      "event": "push",
      "status": "completed",
      "conclusion": "failure",
      "created_at": "2025-11-14T19:25:08Z",
      "updated_at": "2025-11-14T19:25:08Z",
      "duration_ms": 0
    },
    {
      "id": 19375190694,
      "name": ".github/workflows/ci.yml",
      "event": "push",
      "status": "completed",
      "conclusion": "failure",
      "created_at": "2025-11-14T19:19:47Z",
      "updated_at": "2025-11-14T19:19:47Z",
      "duration_ms": 0
    },
    {
      "id": 19375190574,
      "name": ".github/workflows/daily-ltdd-telemetry.yml",
      "event": "push",
      "status": "completed",
      "conclusion": "failure",
      "created_at": "2025-11-14T19:19:46Z",
      "updated_at": "2025-11-14T19:19:46Z",
      "duration_ms": 0
    },
    {
      "id": 19375136836,
      "name": ".github/workflows/ci.yml",
      "event": "push",
      "status": "completed",
      "conclusion": "failure",
      "created_at": "2025-11-14T19:17:34Z",
      "updated_at": "2025-11-14T19:17:34Z",
      "duration_ms": 0
    },
    {
      "id": 19375136992,
      "name": ".github/workflows/daily-ltdd-telemetry.yml",
      "event": "push",
      "status": "completed",
      "conclusion": "failure",
      "created_at": "2025-11-14T19:17:34Z",
      "updated_at": "2025-11-14T19:17:34Z",
      "duration_ms": 0
    },
    {
      "id": 19372797358,
      "name": ".github/workflows/daily-ltdd-telemetry.yml",
      "event": "push",
      "status": "completed",
      "conclusion": "failure",
      "created_at": "2025-11-14T17:39:51Z",
      "updated_at": "2025-11-14T17:39:51Z",
      "duration_ms": 0
    },
    {
      "id": 19372797250,
      "name": ".github/workflows/ci.yml",
      "event": "push",
      "status": "completed",
      "conclusion": "failure",
      "created_at": "2025-11-14T17:39:50Z",
      "updated_at": "2025-11-14T17:39:50Z",
      "duration_ms": 0
    },
    {
      "id": 19372753968,
      "name": ".github/workflows/daily-ltdd-telemetry.yml",
      "event": "push",
      "status": "completed",
      "conclusion": "failure",
      "created_at": "2025-11-14T17:38:00Z",
      "updated_at": "2025-11-14T17:38:00Z",
      "duration_ms": 0
    },
    {
      "id": 19372754104,
      "name": ".github/workflows/ci.yml",
      "event": "push",
      "status": "completed",
      "conclusion": "failure",
      "created_at": "2025-11-14T17:38:00Z",
      "updated_at": "2025-11-14T17:38:00Z",
      "duration_ms": 0
    },
    {
      "id": 19372345059,
      "name": "Verify Complete LTDD Hardening",
      "event": "push",
      "status": "completed",
      "conclusion": "failure",
      "created_at": "2025-11-14T17:22:24Z",
      "updated_at": "2025-11-14T17:22:35Z",
      "duration_ms": 11000
    },
    {
      "id": 19372345016,
      "name": "Prod Guardrails",
      "event": "push",
      "status": "completed",
      "conclusion": "failure",
      "created_at": "2025-11-14T17:22:24Z",
      "updated_at": "2025-11-14T17:23:04Z",
      "duration_ms": 40000
    }
  ]
}
