{
  "since": "2026-02-21T04:02:43Z",
  "total_runs": 226,
  "runs": [
    {
      "id": 22269927635,
      "name": "RAG Retrieval Scorecard",
      "event": "push",
      "status": "completed",
      "conclusion": "success",
      "created_at": "2026-02-22T03:51:37Z",
      "updated_at": "2026-02-22T03:52:17Z",
      "duration_ms": 40000
    },
    {
      "id": 22269927640,
      "name": "Prod Guardrails",
      "event": "push",
      "status": "completed",
      "conclusion": "failure",
      "created_at": "2026-02-22T03:51:37Z",
      "updated_at": "2026-02-22T03:55:40Z",
      "duration_ms": 243000
    },
    {
      "id": 22269927674,
      "name": "Release (Golden Path)",
      "event": "push",
      "status": "in_progress",
      "conclusion": null,
      "created_at": "2026-02-22T03:51:37Z",
      "updated_at": "2026-02-22T03:59:26Z",
      "duration_ms": 469000
    },
    {
      "id": 22269927645,
      "name": "Lock Tests (Production Sentinel)",
      "event": "push",
      "status": "completed",
      "conclusion": "failure",
      "created_at": "2026-02-22T03:51:37Z",
      "updated_at": "2026-02-22T04:01:52Z",
      "duration_ms": 615000
    },
    {
      "id": 22269927372,
      "name": ".github/workflows/ltdd-sync-branch-protection.yml",
      "event": "push",
      "status": "completed",
      "conclusion": "failure",
      "created_at": "2026-02-22T03:51:36Z",
      "updated_at": "2026-02-22T03:51:36Z",
      "duration_ms": 0
    },
    {
      "id": 22269927444,
      "name": ".github/workflows/ci.yml",
      "event": "push",
      "status": "completed",
      "conclusion": "failure",
      "created_at": "2026-02-22T03:51:36Z",
      "updated_at": "2026-02-22T03:51:36Z",
      "duration_ms": 0
    },
    {
      "id": 22269927498,
      "name": ".github/workflows/hardening-gate.yml",
      "event": "push",
      "status": "completed",
      "conclusion": "failure",
      "created_at": "2026-02-22T03:51:36Z",
      "updated_at": "2026-02-22T03:51:36Z",
      "duration_ms": 0
    },
    {
      "id": 22269927310,
      "name": ".github/workflows/daily-ltdd-telemetry.yml",
      "event": "push",
      "status": "completed",
      "conclusion": "failure",
      "created_at": "2026-02-22T03:51:35Z",
      "updated_at": "2026-02-22T03:51:35Z",
      "duration_ms": 0
    },
    {
      "id": 22269841926,
      "name": ".github/workflows/ltdd-sync-branch-protection.yml",
      "event": "push",
      "status": "completed",
      "conclusion": "failure",
      "created_at": "2026-02-22T03:45:02Z",
      "updated_at": "2026-02-22T03:45:02Z",
      "duration_ms": 0
    },
    {
      "id": 22269841999,
      "name": ".github/workflows/daily-ltdd-telemetry.yml",
      "event": "push",
      "status": "completed",
      "conclusion": "failure",
      "created_at": "2026-02-22T03:45:02Z",
      "updated_at": "2026-02-22T03:45:02Z",
      "duration_ms": 0
    },
    {
      "id": 22269842092,
      "name": ".github/workflows/hardening-gate.yml",
      "event": "push",
      "status": "completed",
      "conclusion": "failure",
      "created_at": "2026-02-22T03:45:02Z",
      "updated_at": "2026-02-22T03:45:02Z",
      "duration_ms": 0
    },
    {
      "id": 22269841864,
      "name": ".github/workflows/ci.yml",
      "event": "push",
      "status": "completed",
      "conclusion": "failure",
      "created_at": "2026-02-22T03:45:01Z",
      "updated_at": "2026-02-22T03:45:01Z",
      "duration_ms": 0
    },
    {
      "id": 22268944036,
      "name": ".github/workflows/ci.yml",
      "event": "push",
      "status": "completed",
      "conclusion": "failure",
      "created_at": "2026-02-22T02:34:40Z",
      "updated_at": "2026-02-22T02:34:40Z",
      "duration_ms": 0
    },
    {
      "id": 22268944159,
      "name": "RAG Retrieval Scorecard",
      "event": "push",
      "status": "completed",
      "conclusion": "success",
      "created_at": "2026-02-22T02:34:40Z",
      "updated_at": "2026-02-22T02:35:24Z",
      "duration_ms": 44000
    },
    {
      "id": 22268944153,
      "name": "Prod Guardrails",
      "event": "push",
      "status": "completed",
      "conclusion": "failure",
      "created_at": "2026-02-22T02:34:40Z",
      "updated_at": "2026-02-22T02:38:47Z",
      "duration_ms": 247000
    },
    {
      "id": 22268944155,
      "name": "Lock Tests (Production Sentinel)",
      "event": "push",
      "status": "completed",
      "conclusion": "failure",
      "created_at": "2026-02-22T02:34:40Z",
      "updated_at": "2026-02-22T02:44:32Z",
      "duration_ms": 592000
    },
    {
      "id": 22268944202,
      "name": "Release (Golden Path)",
      "event": "push",
      "status": "completed",
      "conclusion": "failure",
      "created_at": "2026-02-22T02:34:40Z",
      "updated_at": "2026-02-22T02:52:19Z",
      "duration_ms": 1059000
    },
    {
      "id": 22268943887,
      "name": ".github/workflows/daily-ltdd-telemetry.yml",
      "event": "push",
      "status": "completed",
      "conclusion": "failure",
      "created_at": "2026-02-22T02:34:39Z",
      "updated_at": "2026-02-22T02:34:39Z",
      "duration_ms": 0
    },
    {
      "id": 22268943974,
      "name": ".github/workflows/ltdd-sync-branch-protection.yml",
      "event": "push",
      "status": "completed",
      "conclusion": "failure",
      "created_at": "2026-02-22T02:34:39Z",
      "updated_at": "2026-02-22T02:34:39Z",
      "duration_ms": 0
    },
    {
      "id": 22268943809,
      "name": ".github/workflows/hardening-gate.yml",
      "event": "push",
      "status": "completed",
      "conclusion": "failure",
      "created_at": "2026-02-22T02:34:38Z",
      "updated_at": "2026-02-22T02:34:38Z",
      "duration_ms": 0
    },
    {
      "id": 22268857862,
      "name": "Ping (Actions Test)",
      "event": "push",
      "status": "completed",
      "conclusion": "success",
      "created_at": "2026-02-22T02:27:55Z",
      "updated_at": "2026-02-22T02:28:03Z",
      "duration_ms": 8000
    },
    {
      "id": 22268857619,
      "name": ".github/workflows/hardening-gate.yml",
      "event": "push",
      "status": "completed",
      "conclusion": "failure",
      "created_at": "2026-02-22T02:27:54Z",
      "updated_at": "2026-02-22T02:27:54Z",
      "duration_ms": 0
    },
    {
      "id": 22268857698,
      "name": ".github/workflows/ci.yml",
      "event": "push",
      "status": "completed",
      "conclusion": "failure",
      "created_at": "2026-02-22T02:27:54Z",
      "updated_at": "2026-02-22T02:27:54Z",
      "duration_ms": 0
    },
    {
      "id": 22268857502,
      "name": ".github/workflows/daily-ltdd-telemetry.yml",
      "event": "push",
      "status": "completed",
      "conclusion": "failure",
      "created_at": "2026-02-22T02:27:53Z",
      "updated_at": "2026-02-22T02:27:53Z",
      "duration_ms": 0
    },
    {
      "id": 22268857578,
      "name": ".github/workflows/ltdd-sync-branch-protection.yml",
      "event": "push",
      "status": "completed",
      "conclusion": "failure",
      "created_at": "2026-02-22T02:27:53Z",
      "updated_at": "2026-02-22T02:27:53Z",
      "duration_ms": 0
    },
    {
      "id": 22268370151,
      "name": "Lock Tests (Production Sentinel)",
      "event": "push",
      "status": "completed",
      "conclusion": "failure",
      "created_at": "2026-02-22T01:52:16Z",
      "updated_at": "2026-02-22T01:55:23Z",
      "duration_ms": 187000
    },
    {
      "id": 22268370152,
      "name": "Prod Guardrails",
      "event": "push",
      "status": "completed",
      "conclusion": "failure",
      "created_at": "2026-02-22T01:52:16Z",
      "updated_at": "2026-02-22T01:56:16Z",
      "duration_ms": 240000
    },
    {
      "id": 22268370180,
      "name": "Release (Golden Path)",
      "event": "push",
      "status": "completed",
      "conclusion": "success",
      "created_at": "2026-02-22T01:52:16Z",
      "updated_at": "2026-02-22T02:12:40Z",
      "duration_ms": 1224000
    },
    {
      "id": 22268370021,
      "name": ".github/workflows/ltdd-sync-branch-protection.yml",
      "event": "push",
      "status": "completed",
      "conclusion": "failure",
      "created_at": "2026-02-22T01:52:15Z",
      "updated_at": "2026-02-22T01:52:15Z",
      "duration_ms": 0
    },
    {
      "id": 22268369809,
      "name": ".github/workflows/ci.yml",
      "event": "push",
      "status": "completed",
      "conclusion": "failure",
      "created_at": "2026-02-22T01:52:14Z",
      "updated_at": "2026-02-22T01:52:14Z",
      "duration_ms": 0
    },
    {
      "id": 22268369879,
      "name": ".github/workflows/hardening-gate.yml",
      "event": "push",
      "status": "completed",
      "conclusion": "failure",
      "created_at": "2026-02-22T01:52:14Z",
      "updated_at": "2026-02-22T01:52:14Z",
      "duration_ms": 0
    },
    {
      "id": 22268369949,
      "name": ".github/workflows/daily-ltdd-telemetry.yml",
      "event": "push",
      "status": "completed",
      "conclusion": "failure",
      "created_at": "2026-02-22T01:52:14Z",
      "updated_at": "2026-02-22T01:52:14Z",
      "duration_ms": 0
    },
    {
      "id": 22268267477,
      "name": ".github/workflows/ci.yml",
      "event": "push",
      "status": "completed",
      "conclusion": "failure",
      "created_at": "2026-02-22T01:44:18Z",
      "updated_at": "2026-02-22T01:44:18Z",
      "duration_ms": 0
    },
    {
      "id": 22268267608,
      "name": "Ping (Actions Test)",
      "event": "push",
      "status": "completed",
      "conclusion": "success",
      "created_at": "2026-02-22T01:44:18Z",
      "updated_at": "2026-02-22T01:44:26Z",
      "duration_ms": 8000
    },
    {
      "id": 22268267227,
      "name": ".github/workflows/daily-ltdd-telemetry.yml",
      "event": "push",
      "status": "completed",
      "conclusion": "failure",
      "created_at": "2026-02-22T01:44:17Z",
      "updated_at": "2026-02-22T01:44:17Z",
      "duration_ms": 0
    },
    {
      "id": 22268267323,
      "name": ".github/workflows/hardening-gate.yml",
      "event": "push",
      "status": "completed",
      "conclusion": "failure",
      "created_at": "2026-02-22T01:44:17Z",
      "updated_at": "2026-02-22T01:44:17Z",
      "duration_ms": 0
    },
    {
      "id": 22268267410,
      "name": ".github/workflows/ltdd-sync-branch-protection.yml",
      "event": "push",
      "status": "completed",
      "conclusion": "failure",
      "created_at": "2026-02-22T01:44:17Z",
      "updated_at": "2026-02-22T01:44:17Z",
      "duration_ms": 0
    },
    {
      "id": 22267756263,
      "name": ".github/workflows/hardening-gate.yml",
      "event": "push",
      "status": "completed",
      "conclusion": "failure",
      "created_at": "2026-02-22T01:05:18Z",
      "updated_at": "2026-02-22T01:05:18Z",
      "duration_ms": 0
    },
    {
      "id": 22267756420,
      "name": "Prod Guardrails",
      "event": "push",
      "status": "completed",
      "conclusion": "failure",
      "created_at": "2026-02-22T01:05:18Z",
      "updated_at": "2026-02-22T01:10:39Z",
      "duration_ms": 321000
    },
    {
      "id": 22267756422,
      "name": "Lock Tests (Production Sentinel)",
      "event": "push",
      "status": "completed",
      "conclusion": "failure",
      "created_at": "2026-02-22T01:05:18Z",
      "updated_at": "2026-02-22T01:12:00Z",
      "duration_ms": 402000
    },
    {
      "id": 22267756458,
      "name": "Release (Golden Path)",
      "event": "push",
      "status": "completed",
      "conclusion": "failure",
      "created_at": "2026-02-22T01:05:18Z",
      "updated_at": "2026-02-22T01:18:01Z",
      "duration_ms": 763000
    },
    {
      "id": 22267756117,
      "name": ".github/workflows/daily-ltdd-telemetry.yml",
      "event": "push",
      "status": "completed",
      "conclusion": "failure",
      "created_at": "2026-02-22T01:05:17Z",
      "updated_at": "2026-02-22T01:05:17Z",
      "duration_ms": 0
    },
    {
      "id": 22267756043,
      "name": ".github/workflows/ltdd-sync-branch-protection.yml",
      "event": "push",
      "status": "completed",
      "conclusion": "failure",
      "created_at": "2026-02-22T01:05:17Z",
      "updated_at": "2026-02-22T01:05:17Z",
      "duration_ms": 0
    },
    {
      "id": 22267756207,
      "name": ".github/workflows/ci.yml",
      "event": "push",
      "status": "completed",
      "conclusion": "failure",
      "created_at": "2026-02-22T01:05:17Z",
      "updated_at": "2026-02-22T01:05:17Z",
      "duration_ms": 0
    },
    {
      "id": 22267600092,
      "name": "Ping (Actions Test)",
      "event": "push",
      "status": "completed",
      "conclusion": "success",
      "created_at": "2026-02-22T00:54:03Z",
      "updated_at": "2026-02-22T00:54:09Z",
      "duration_ms": 6000
    },
    {
      "id": 22267599741,
      "name": ".github/workflows/ltdd-sync-branch-protection.yml",
      "event": "push",
      "status": "completed",
      "conclusion": "failure",
      "created_at": "2026-02-22T00:54:02Z",
      "updated_at": "2026-02-22T00:54:02Z",
      "duration_ms": 0
    },
    {
      "id": 22267599814,
      "name": ".github/workflows/ci.yml",
      "event": "push",
      "status": "completed",
      "conclusion": "failure",
      "created_at": "2026-02-22T00:54:02Z",
      "updated_at": "2026-02-22T00:54:02Z",
      "duration_ms": 0
    },
    {
      "id": 22267599900,
      "name": ".github/workflows/hardening-gate.yml",
      "event": "push",
      "status": "completed",
      "conclusion": "failure",
      "created_at": "2026-02-22T00:54:02Z",
      "updated_at": "2026-02-22T00:54:02Z",
      "duration_ms": 0
    },
    {
      "id": 22267599684,
      "name": ".github/workflows/daily-ltdd-telemetry.yml",
      "event": "push",
      "status": "completed",
      "conclusion": "failure",
      "created_at": "2026-02-22T00:54:01Z",
      "updated_at": "2026-02-22T00:54:01Z",
      "duration_ms": 0
    },
    {
      "id": 22267573508,
      "name": "Ping (Actions Test)",
      "event": "push",
      "status": "completed",
      "conclusion": "success",
      "created_at": "2026-02-22T00:52:06Z",
      "updated_at": "2026-02-22T00:52:12Z",
      "duration_ms": 6000
    },
    {
      "id": 22267573378,
      "name": ".github/workflows/ci.yml",
      "event": "push",
      "status": "completed",
      "conclusion": "failure",
      "created_at": "2026-02-22T00:52:06Z",
      "updated_at": "2026-02-22T00:52:06Z",
      "duration_ms": 0
    },
    {
      "id": 22267573144,
      "name": ".github/workflows/hardening-gate.yml",
      "event": "push",
      "status": "completed",
      "conclusion": "failure",
      "created_at": "2026-02-22T00:52:05Z",
      "updated_at": "2026-02-22T00:52:05Z",
      "duration_ms": 0
    },
    {
      "id": 22267573208,
      "name": ".github/workflows/ltdd-sync-branch-protection.yml",
      "event": "push",
      "status": "completed",
      "conclusion": "failure",
      "created_at": "2026-02-22T00:52:05Z",
      "updated_at": "2026-02-22T00:52:05Z",
      "duration_ms": 0
    },
    {
      "id": 22267573274,
      "name": ".github/workflows/daily-ltdd-telemetry.yml",
      "event": "push",
      "status": "completed",
      "conclusion": "failure",
      "created_at": "2026-02-22T00:52:05Z",
      "updated_at": "2026-02-22T00:52:05Z",
      "duration_ms": 0
    },
    {
      "id": 22267225807,
      "name": "Release (Golden Path)",
      "event": "push",
      "status": "completed",
      "conclusion": "success",
      "created_at": "2026-02-22T00:27:35Z",
      "updated_at": "2026-02-22T00:43:49Z",
      "duration_ms": 974000
    },
    {
      "id": 22267225766,
      "name": "Prod Guardrails",
      "event": "push",
      "status": "completed",
      "conclusion": "failure",
      "created_at": "2026-02-22T00:27:35Z",
      "updated_at": "2026-02-22T00:31:37Z",
      "duration_ms": 242000
    },
    {
      "id": 22267225769,
      "name": "Lock Tests (Production Sentinel)",
      "event": "push",
      "status": "completed",
      "conclusion": "failure",
      "created_at": "2026-02-22T00:27:35Z",
      "updated_at": "2026-02-22T00:38:34Z",
      "duration_ms": 659000
    },
    {
      "id": 22267225527,
      "name": ".github/workflows/ci.yml",
      "event": "push",
      "status": "completed",
      "conclusion": "failure",
      "created_at": "2026-02-22T00:27:34Z",
      "updated_at": "2026-02-22T00:27:34Z",
      "duration_ms": 0
    },
    {
      "id": 22267225602,
      "name": ".github/workflows/hardening-gate.yml",
      "event": "push",
      "status": "completed",
      "conclusion": "failure",
      "created_at": "2026-02-22T00:27:34Z",
      "updated_at": "2026-02-22T00:27:34Z",
      "duration_ms": 0
    },
    {
      "id": 22267225380,
      "name": ".github/workflows/ltdd-sync-branch-protection.yml",
      "event": "push",
      "status": "completed",
      "conclusion": "failure",
      "created_at": "2026-02-22T00:27:33Z",
      "updated_at": "2026-02-22T00:27:33Z",
      "duration_ms": 0
    },
    {
      "id": 22267225449,
      "name": ".github/workflows/daily-ltdd-telemetry.yml",
      "event": "push",
      "status": "completed",
      "conclusion": "failure",
      "created_at": "2026-02-22T00:27:33Z",
      "updated_at": "2026-02-22T00:27:33Z",
      "duration_ms": 0
    },
    {
      "id": 22267089218,
      "name": ".github/workflows/ci.yml",
      "event": "push",
      "status": "completed",
      "conclusion": "failure",
      "created_at": "2026-02-22T00:17:43Z",
      "updated_at": "2026-02-22T00:17:43Z",
      "duration_ms": 0
    },
    {
      "id": 22267089029,
      "name": ".github/workflows/ltdd-sync-branch-protection.yml",
      "event": "push",
      "status": "completed",
      "conclusion": "failure",
      "created_at": "2026-02-22T00:17:42Z",
      "updated_at": "2026-02-22T00:17:42Z",
      "duration_ms": 0
    },
    {
      "id": 22267089078,
      "name": ".github/workflows/hardening-gate.yml",
      "event": "push",
      "status": "completed",
      "conclusion": "failure",
      "created_at": "2026-02-22T00:17:42Z",
      "updated_at": "2026-02-22T00:17:42Z",
      "duration_ms": 0
    },
    {
      "id": 22267089155,
      "name": ".github/workflows/daily-ltdd-telemetry.yml",
      "event": "push",
      "status": "completed",
      "conclusion": "failure",
      "created_at": "2026-02-22T00:17:42Z",
      "updated_at": "2026-02-22T00:17:42Z",
      "duration_ms": 0
    },
    {
      "id": 22267055516,
      "name": ".github/workflows/ci.yml",
      "event": "push",
      "status": "completed",
      "conclusion": "failure",
      "created_at": "2026-02-22T00:15:11Z",
      "updated_at": "2026-02-22T00:15:11Z",
      "duration_ms": 0
    },
    {
      "id": 22267055601,
      "name": ".github/workflows/hardening-gate.yml",
      "event": "push",
      "status": "completed",
      "conclusion": "failure",
      "created_at": "2026-02-22T00:15:11Z",
      "updated_at": "2026-02-22T00:15:11Z",
      "duration_ms": 0
    },
    {
      "id": 22267055335,
      "name": ".github/workflows/ltdd-sync-branch-protection.yml",
      "event": "push",
      "status": "completed",
      "conclusion": "failure",
      "created_at": "2026-02-22T00:15:10Z",
      "updated_at": "2026-02-22T00:15:10Z",
      "duration_ms": 0
    },
    {
      "id": 22267055413,
      "name": ".github/workflows/daily-ltdd-telemetry.yml",
      "event": "push",
      "status": "completed",
      "conclusion": "failure",
      "created_at": "2026-02-22T00:15:10Z",
      "updated_at": "2026-02-22T00:15:10Z",
      "duration_ms": 0
    },
    {
      "id": 22266746716,
      "name": "Release (Golden Path)",
      "event": "push",
      "status": "completed",
      "conclusion": "success",
      "created_at": "2026-02-21T23:52:38Z",
      "updated_at": "2026-02-22T00:10:07Z",
      "duration_ms": 1049000
    },
    {
      "id": 22266746492,
      "name": ".github/workflows/ltdd-sync-branch-protection.yml",
      "event": "push",
      "status": "completed",
      "conclusion": "failure",
      "created_at": "2026-02-21T23:52:37Z",
      "updated_at": "2026-02-21T23:52:37Z",
      "duration_ms": 0
    },
    {
      "id": 22266746581,
      "name": ".github/workflows/hardening-gate.yml",
      "event": "push",
      "status": "completed",
      "conclusion": "failure",
      "created_at": "2026-02-21T23:52:37Z",
      "updated_at": "2026-02-21T23:52:37Z",
      "duration_ms": 0
    },
    {
      "id": 22266746690,
      "name": "Prod Guardrails",
      "event": "push",
      "status": "completed",
      "conclusion": "failure",
      "created_at": "2026-02-21T23:52:37Z",
      "updated_at": "2026-02-21T23:56:59Z",
      "duration_ms": 262000
    },
    {
      "id": 22266746691,
      "name": "Lock Tests (Production Sentinel)",
      "event": "push",
      "status": "completed",
      "conclusion": "failure",
      "created_at": "2026-02-21T23:52:37Z",
      "updated_at": "2026-02-22T00:00:56Z",
      "duration_ms": 499000
    },
    {
      "id": 22266746397,
      "name": ".github/workflows/daily-ltdd-telemetry.yml",
      "event": "push",
      "status": "completed",
      "conclusion": "failure",
      "created_at": "2026-02-21T23:52:36Z",
      "updated_at": "2026-02-21T23:52:36Z",
      "duration_ms": 0
    },
    {
      "id": 22266746446,
      "name": ".github/workflows/ci.yml",
      "event": "push",
      "status": "completed",
      "conclusion": "failure",
      "created_at": "2026-02-21T23:52:36Z",
      "updated_at": "2026-02-21T23:52:36Z",
      "duration_ms": 0
    },
    {
      "id": 22266660740,
      "name": ".github/workflows/ltdd-sync-branch-protection.yml",
      "event": "push",
      "status": "completed",
      "conclusion": "failure",
      "created_at": "2026-02-21T23:46:16Z",
      "updated_at": "2026-02-21T23:46:16Z",
      "duration_ms": 0
    },
    {
      "id": 22266660785,
      "name": ".github/workflows/hardening-gate.yml",
      "event": "push",
      "status": "completed",
      "conclusion": "failure",
      "created_at": "2026-02-21T23:46:16Z",
      "updated_at": "2026-02-21T23:46:16Z",
      "duration_ms": 0
    },
    {
      "id": 22266660820,
      "name": ".github/workflows/daily-ltdd-telemetry.yml",
      "event": "push",
      "status": "completed",
      "conclusion": "failure",
      "created_at": "2026-02-21T23:46:16Z",
      "updated_at": "2026-02-21T23:46:16Z",
      "duration_ms": 0
    },
    {
      "id": 22266660665,
      "name": ".github/workflows/ci.yml",
      "event": "push",
      "status": "completed",
      "conclusion": "failure",
      "created_at": "2026-02-21T23:46:15Z",
      "updated_at": "2026-02-21T23:46:15Z",
      "duration_ms": 0
    },
    {
      "id": 22266334969,
      "name": "Release (Golden Path)",
      "event": "push",
      "status": "completed",
      "conclusion": "success",
      "created_at": "2026-02-21T23:22:23Z",
      "updated_at": "2026-02-21T23:37:53Z",
      "duration_ms": 930000
    },
    {
      "id": 22266334625,
      "name": ".github/workflows/hardening-gate.yml",
      "event": "push",
      "status": "completed",
      "conclusion": "failure",
      "created_at": "2026-02-21T23:22:22Z",
      "updated_at": "2026-02-21T23:22:22Z",
      "duration_ms": 0
    },
    {
      "id": 22266334922,
      "name": "Prod Guardrails",
      "event": "push",
      "status": "completed",
      "conclusion": "failure",
      "created_at": "2026-02-21T23:22:22Z",
      "updated_at": "2026-02-21T23:26:44Z",
      "duration_ms": 262000
    },
    {
      "id": 22266334927,
      "name": "Lock Tests (Production Sentinel)",
      "event": "push",
      "status": "completed",
      "conclusion": "failure",
      "created_at": "2026-02-21T23:22:22Z",
      "updated_at": "2026-02-21T23:30:39Z",
      "duration_ms": 497000
    },
    {
      "id": 22266334261,
      "name": ".github/workflows/daily-ltdd-telemetry.yml",
      "event": "push",
      "status": "completed",
      "conclusion": "failure",
      "created_at": "2026-02-21T23:22:21Z",
      "updated_at": "2026-02-21T23:22:21Z",
      "duration_ms": 0
    },
    {
      "id": 22266334388,
      "name": ".github/workflows/ltdd-sync-branch-protection.yml",
      "event": "push",
      "status": "completed",
      "conclusion": "failure",
      "created_at": "2026-02-21T23:22:21Z",
      "updated_at": "2026-02-21T23:22:21Z",
      "duration_ms": 0
    },
    {
      "id": 22266334508,
      "name": ".github/workflows/ci.yml",
      "event": "push",
      "status": "completed",
      "conclusion": "failure",
      "created_at": "2026-02-21T23:22:21Z",
      "updated_at": "2026-02-21T23:22:21Z",
      "duration_ms": 0
    },
    {
      "id": 22266245612,
      "name": "Ping (Actions Test)",
      "event": "push",
      "status": "completed",
      "conclusion": "success",
      "created_at": "2026-02-21T23:16:01Z",
      "updated_at": "2026-02-21T23:16:08Z",
      "duration_ms": 7000
    },
    {
      "id": 22266245315,
      "name": ".github/workflows/hardening-gate.yml",
      "event": "push",
      "status": "completed",
      "conclusion": "failure",
      "created_at": "2026-02-21T23:16:00Z",
      "updated_at": "2026-02-21T23:16:00Z",
      "duration_ms": 0
    },
    {
      "id": 22266245411,
      "name": ".github/workflows/ci.yml",
      "event": "push",
      "status": "completed",
      "conclusion": "failure",
      "created_at": "2026-02-21T23:16:00Z",
      "updated_at": "2026-02-21T23:16:00Z",
      "duration_ms": 0
    },
    {
      "id": 22266245123,
      "name": ".github/workflows/daily-ltdd-telemetry.yml",
      "event": "push",
      "status": "completed",
      "conclusion": "failure",
      "created_at": "2026-02-21T23:15:59Z",
      "updated_at": "2026-02-21T23:15:59Z",
      "duration_ms": 0
    },
    {
      "id": 22266245211,
      "name": ".github/workflows/ltdd-sync-branch-protection.yml",
      "event": "push",
      "status": "completed",
      "conclusion": "failure",
      "created_at": "2026-02-21T23:15:59Z",
      "updated_at": "2026-02-21T23:15:59Z",
      "duration_ms": 0
    },
    {
      "id": 22266134199,
      "name": ".github/workflows/hardening-gate.yml",
      "event": "push",
      "status": "completed",
      "conclusion": "failure",
      "created_at": "2026-02-21T23:07:51Z",
      "updated_at": "2026-02-21T23:07:51Z",
      "duration_ms": 0
    },
    {
      "id": 22266134262,
      "name": ".github/workflows/ci.yml",
      "event": "push",
      "status": "completed",
      "conclusion": "failure",
      "created_at": "2026-02-21T23:07:51Z",
      "updated_at": "2026-02-21T23:07:51Z",
      "duration_ms": 0
    },
    {
      "id": 22266134083,
      "name": ".github/workflows/daily-ltdd-telemetry.yml",
      "event": "push",
      "status": "completed",
      "conclusion": "failure",
      "created_at": "2026-02-21T23:07:50Z",
      "updated_at": "2026-02-21T23:07:50Z",
      "duration_ms": 0
    },
    {
      "id": 22266134128,
      "name": ".github/workflows/ltdd-sync-branch-protection.yml",
      "event": "push",
      "status": "completed",
      "conclusion": "failure",
      "created_at": "2026-02-21T23:07:50Z",
      "updated_at": "2026-02-21T23:07:50Z",
      "duration_ms": 0
    },
    {
      "id": 22265574034,
      "name": ".github/workflows/ci.yml",
      "event": "push",
      "status": "completed",
      "conclusion": "failure",
      "created_at": "2026-02-21T22:27:45Z",
      "updated_at": "2026-02-21T22:27:45Z",
      "duration_ms": 0
    },
    {
      "id": 22265574211,
      "name": "RAG Retrieval Scorecard",
      "event": "push",
      "status": "completed",
      "conclusion": "success",
      "created_at": "2026-02-21T22:27:45Z",
      "updated_at": "2026-02-21T22:28:28Z",
      "duration_ms": 43000
    },
    {
      "id": 22265574214,
      "name": "Prod Guardrails",
      "event": "push",
      "status": "completed",
      "conclusion": "failure",
      "created_at": "2026-02-21T22:27:45Z",
      "updated_at": "2026-02-21T22:32:06Z",
      "duration_ms": 261000
    },
    {
      "id": 22265574226,
      "name": "Lock Tests (Production Sentinel)",
      "event": "push",
      "status": "completed",
      "conclusion": "failure",
      "created_at": "2026-02-21T22:27:45Z",
      "updated_at": "2026-02-21T22:36:14Z",
      "duration_ms": 509000
    }
  ]
}
