{
  "since": "2026-06-10T04:52:39Z",
  "total_runs": 93,
  "runs": [
    {
      "id": 27303370189,
      "name": ".github/workflows/ci.yml",
      "event": "push",
      "status": "completed",
      "conclusion": "failure",
      "created_at": "2026-06-10T20:12:59Z",
      "updated_at": "2026-06-10T20:12:59Z",
      "duration_ms": 0
    },
    {
      "id": 27303369057,
      "name": ".github/workflows/ltdd-sync-branch-protection.yml",
      "event": "push",
      "status": "completed",
      "conclusion": "failure",
      "created_at": "2026-06-10T20:12:58Z",
      "updated_at": "2026-06-10T20:12:58Z",
      "duration_ms": 0
    },
    {
      "id": 27303367629,
      "name": ".github/workflows/daily-ltdd-telemetry.yml",
      "event": "push",
      "status": "completed",
      "conclusion": "failure",
      "created_at": "2026-06-10T20:12:57Z",
      "updated_at": "2026-06-10T20:12:57Z",
      "duration_ms": 0
    },
    {
      "id": 27303368515,
      "name": ".github/workflows/hardening-gate.yml",
      "event": "push",
      "status": "completed",
      "conclusion": "failure",
      "created_at": "2026-06-10T20:12:57Z",
      "updated_at": "2026-06-10T20:12:57Z",
      "duration_ms": 0
    },
    {
      "id": 27301497611,
      "name": ".github/workflows/daily-ltdd-telemetry.yml",
      "event": "push",
      "status": "completed",
      "conclusion": "failure",
      "created_at": "2026-06-10T19:41:33Z",
      "updated_at": "2026-06-10T19:41:33Z",
      "duration_ms": 0
    },
    {
      "id": 27301496773,
      "name": ".github/workflows/hardening-gate.yml",
      "event": "push",
      "status": "completed",
      "conclusion": "failure",
      "created_at": "2026-06-10T19:41:32Z",
      "updated_at": "2026-06-10T19:41:32Z",
      "duration_ms": 0
    },
    {
      "id": 27301495715,
      "name": ".github/workflows/ci.yml",
      "event": "push",
      "status": "completed",
      "conclusion": "failure",
      "created_at": "2026-06-10T19:41:31Z",
      "updated_at": "2026-06-10T19:41:31Z",
      "duration_ms": 0
    },
    {
      "id": 27301494736,
      "name": ".github/workflows/ltdd-sync-branch-protection.yml",
      "event": "push",
      "status": "completed",
      "conclusion": "failure",
      "created_at": "2026-06-10T19:41:30Z",
      "updated_at": "2026-06-10T19:41:30Z",
      "duration_ms": 0
    },
    {
      "id": 27294885033,
      "name": ".github/workflows/hardening-gate.yml",
      "event": "push",
      "status": "completed",
      "conclusion": "failure",
      "created_at": "2026-06-10T17:46:15Z",
      "updated_at": "2026-06-10T17:46:15Z",
      "duration_ms": 0
    },
    {
      "id": 27294884315,
      "name": ".github/workflows/ci.yml",
      "event": "push",
      "status": "completed",
      "conclusion": "failure",
      "created_at": "2026-06-10T17:46:14Z",
      "updated_at": "2026-06-10T17:46:14Z",
      "duration_ms": 0
    },
    {
      "id": 27294883658,
      "name": ".github/workflows/daily-ltdd-telemetry.yml",
      "event": "push",
      "status": "completed",
      "conclusion": "failure",
      "created_at": "2026-06-10T17:46:13Z",
      "updated_at": "2026-06-10T17:46:13Z",
      "duration_ms": 0
    },
    {
      "id": 27294882750,
      "name": ".github/workflows/ltdd-sync-branch-protection.yml",
      "event": "push",
      "status": "completed",
      "conclusion": "failure",
      "created_at": "2026-06-10T17:46:12Z",
      "updated_at": "2026-06-10T17:46:12Z",
      "duration_ms": 0
    },
    {
      "id": 27291765719,
      "name": ".github/workflows/ci.yml",
      "event": "push",
      "status": "completed",
      "conclusion": "failure",
      "created_at": "2026-06-10T16:52:52Z",
      "updated_at": "2026-06-10T16:52:52Z",
      "duration_ms": 0
    },
    {
      "id": 27291763831,
      "name": ".github/workflows/daily-ltdd-telemetry.yml",
      "event": "push",
      "status": "completed",
      "conclusion": "failure",
      "created_at": "2026-06-10T16:52:51Z",
      "updated_at": "2026-06-10T16:52:51Z",
      "duration_ms": 0
    },
    {
      "id": 27291763405,
      "name": ".github/workflows/ltdd-sync-branch-protection.yml",
      "event": "push",
      "status": "completed",
      "conclusion": "failure",
      "created_at": "2026-06-10T16:52:50Z",
      "updated_at": "2026-06-10T16:52:50Z",
      "duration_ms": 0
    },
    {
      "id": 27291761841,
      "name": ".github/workflows/hardening-gate.yml",
      "event": "push",
      "status": "completed",
      "conclusion": "failure",
      "created_at": "2026-06-10T16:52:49Z",
      "updated_at": "2026-06-10T16:52:49Z",
      "duration_ms": 0
    },
    {
      "id": 27288655405,
      "name": "Prod Guardrails",
      "event": "push",
      "status": "completed",
      "conclusion": "failure",
      "created_at": "2026-06-10T15:57:43Z",
      "updated_at": "2026-06-10T16:01:52Z",
      "duration_ms": 249000
    },
    {
      "id": 27288655455,
      "name": "Lock Tests (Production Sentinel)",
      "event": "push",
      "status": "completed",
      "conclusion": "failure",
      "created_at": "2026-06-10T15:57:43Z",
      "updated_at": "2026-06-10T16:07:10Z",
      "duration_ms": 567000
    },
    {
      "id": 27288656441,
      "name": "Release (Golden Path)",
      "event": "push",
      "status": "completed",
      "conclusion": "failure",
      "created_at": "2026-06-10T15:57:43Z",
      "updated_at": "2026-06-10T16:34:51Z",
      "duration_ms": 2228000
    },
    {
      "id": 27288652896,
      "name": ".github/workflows/hardening-gate.yml",
      "event": "push",
      "status": "completed",
      "conclusion": "failure",
      "created_at": "2026-06-10T15:57:40Z",
      "updated_at": "2026-06-10T15:57:40Z",
      "duration_ms": 0
    },
    {
      "id": 27288651228,
      "name": ".github/workflows/ci.yml",
      "event": "push",
      "status": "completed",
      "conclusion": "failure",
      "created_at": "2026-06-10T15:57:39Z",
      "updated_at": "2026-06-10T15:57:39Z",
      "duration_ms": 0
    },
    {
      "id": 27288650341,
      "name": ".github/workflows/ltdd-sync-branch-protection.yml",
      "event": "push",
      "status": "completed",
      "conclusion": "failure",
      "created_at": "2026-06-10T15:57:38Z",
      "updated_at": "2026-06-10T15:57:38Z",
      "duration_ms": 0
    },
    {
      "id": 27288649343,
      "name": ".github/workflows/daily-ltdd-telemetry.yml",
      "event": "push",
      "status": "completed",
      "conclusion": "failure",
      "created_at": "2026-06-10T15:57:37Z",
      "updated_at": "2026-06-10T15:57:37Z",
      "duration_ms": 0
    },
    {
      "id": 27288253572,
      "name": ".github/workflows/ci.yml",
      "event": "push",
      "status": "completed",
      "conclusion": "failure",
      "created_at": "2026-06-10T15:50:22Z",
      "updated_at": "2026-06-10T15:50:22Z",
      "duration_ms": 0
    },
    {
      "id": 27288252094,
      "name": ".github/workflows/ltdd-sync-branch-protection.yml",
      "event": "push",
      "status": "completed",
      "conclusion": "failure",
      "created_at": "2026-06-10T15:50:21Z",
      "updated_at": "2026-06-10T15:50:21Z",
      "duration_ms": 0
    },
    {
      "id": 27288252518,
      "name": ".github/workflows/hardening-gate.yml",
      "event": "push",
      "status": "completed",
      "conclusion": "failure",
      "created_at": "2026-06-10T15:50:21Z",
      "updated_at": "2026-06-10T15:50:21Z",
      "duration_ms": 0
    },
    {
      "id": 27288250788,
      "name": ".github/workflows/daily-ltdd-telemetry.yml",
      "event": "push",
      "status": "completed",
      "conclusion": "failure",
      "created_at": "2026-06-10T15:50:19Z",
      "updated_at": "2026-06-10T15:50:19Z",
      "duration_ms": 0
    },
    {
      "id": 27288235401,
      "name": ".github/workflows/ci.yml",
      "event": "push",
      "status": "completed",
      "conclusion": "failure",
      "created_at": "2026-06-10T15:50:04Z",
      "updated_at": "2026-06-10T15:50:04Z",
      "duration_ms": 0
    },
    {
      "id": 27288234268,
      "name": ".github/workflows/ltdd-sync-branch-protection.yml",
      "event": "push",
      "status": "completed",
      "conclusion": "failure",
      "created_at": "2026-06-10T15:50:03Z",
      "updated_at": "2026-06-10T15:50:03Z",
      "duration_ms": 0
    },
    {
      "id": 27288233146,
      "name": ".github/workflows/hardening-gate.yml",
      "event": "push",
      "status": "completed",
      "conclusion": "failure",
      "created_at": "2026-06-10T15:50:02Z",
      "updated_at": "2026-06-10T15:50:02Z",
      "duration_ms": 0
    },
    {
      "id": 27288231971,
      "name": ".github/workflows/daily-ltdd-telemetry.yml",
      "event": "push",
      "status": "completed",
      "conclusion": "failure",
      "created_at": "2026-06-10T15:50:00Z",
      "updated_at": "2026-06-10T15:50:00Z",
      "duration_ms": 0
    },
    {
      "id": 27286720604,
      "name": "Lock Tests (Production Sentinel)",
      "event": "push",
      "status": "completed",
      "conclusion": "failure",
      "created_at": "2026-06-10T15:22:45Z",
      "updated_at": "2026-06-10T15:33:22Z",
      "duration_ms": 637000
    },
    {
      "id": 27286720617,
      "name": "Prod Guardrails",
      "event": "push",
      "status": "completed",
      "conclusion": "failure",
      "created_at": "2026-06-10T15:22:45Z",
      "updated_at": "2026-06-10T15:27:12Z",
      "duration_ms": 267000
    },
    {
      "id": 27286719781,
      "name": "Release (Golden Path)",
      "event": "push",
      "status": "completed",
      "conclusion": "failure",
      "created_at": "2026-06-10T15:22:44Z",
      "updated_at": "2026-06-10T15:37:34Z",
      "duration_ms": 890000
    },
    {
      "id": 27286717822,
      "name": ".github/workflows/ci.yml",
      "event": "push",
      "status": "completed",
      "conclusion": "failure",
      "created_at": "2026-06-10T15:22:42Z",
      "updated_at": "2026-06-10T15:22:42Z",
      "duration_ms": 0
    },
    {
      "id": 27286716216,
      "name": ".github/workflows/hardening-gate.yml",
      "event": "push",
      "status": "completed",
      "conclusion": "failure",
      "created_at": "2026-06-10T15:22:40Z",
      "updated_at": "2026-06-10T15:22:40Z",
      "duration_ms": 0
    },
    {
      "id": 27286714920,
      "name": ".github/workflows/ltdd-sync-branch-protection.yml",
      "event": "push",
      "status": "completed",
      "conclusion": "failure",
      "created_at": "2026-06-10T15:22:39Z",
      "updated_at": "2026-06-10T15:22:39Z",
      "duration_ms": 0
    },
    {
      "id": 27286713777,
      "name": ".github/workflows/daily-ltdd-telemetry.yml",
      "event": "push",
      "status": "completed",
      "conclusion": "failure",
      "created_at": "2026-06-10T15:22:38Z",
      "updated_at": "2026-06-10T15:22:38Z",
      "duration_ms": 0
    },
    {
      "id": 27286192318,
      "name": ".github/workflows/ci.yml",
      "event": "push",
      "status": "completed",
      "conclusion": "failure",
      "created_at": "2026-06-10T15:13:22Z",
      "updated_at": "2026-06-10T15:13:22Z",
      "duration_ms": 0
    },
    {
      "id": 27286190130,
      "name": ".github/workflows/hardening-gate.yml",
      "event": "push",
      "status": "completed",
      "conclusion": "failure",
      "created_at": "2026-06-10T15:13:20Z",
      "updated_at": "2026-06-10T15:13:20Z",
      "duration_ms": 0
    },
    {
      "id": 27286187624,
      "name": ".github/workflows/ltdd-sync-branch-protection.yml",
      "event": "push",
      "status": "completed",
      "conclusion": "failure",
      "created_at": "2026-06-10T15:13:17Z",
      "updated_at": "2026-06-10T15:13:17Z",
      "duration_ms": 0
    },
    {
      "id": 27286185411,
      "name": ".github/workflows/daily-ltdd-telemetry.yml",
      "event": "push",
      "status": "completed",
      "conclusion": "failure",
      "created_at": "2026-06-10T15:13:15Z",
      "updated_at": "2026-06-10T15:13:15Z",
      "duration_ms": 0
    },
    {
      "id": 27286140405,
      "name": ".github/workflows/daily-ltdd-telemetry.yml",
      "event": "push",
      "status": "completed",
      "conclusion": "failure",
      "created_at": "2026-06-10T15:12:30Z",
      "updated_at": "2026-06-10T15:12:30Z",
      "duration_ms": 0
    },
    {
      "id": 27286138821,
      "name": ".github/workflows/ci.yml",
      "event": "push",
      "status": "completed",
      "conclusion": "failure",
      "created_at": "2026-06-10T15:12:29Z",
      "updated_at": "2026-06-10T15:12:29Z",
      "duration_ms": 0
    },
    {
      "id": 27286137589,
      "name": ".github/workflows/hardening-gate.yml",
      "event": "push",
      "status": "completed",
      "conclusion": "failure",
      "created_at": "2026-06-10T15:12:27Z",
      "updated_at": "2026-06-10T15:12:27Z",
      "duration_ms": 0
    },
    {
      "id": 27286136117,
      "name": ".github/workflows/ltdd-sync-branch-protection.yml",
      "event": "push",
      "status": "completed",
      "conclusion": "failure",
      "created_at": "2026-06-10T15:12:26Z",
      "updated_at": "2026-06-10T15:12:26Z",
      "duration_ms": 0
    },
    {
      "id": 27284385140,
      "name": "Prod Guardrails",
      "event": "push",
      "status": "completed",
      "conclusion": "failure",
      "created_at": "2026-06-10T14:44:10Z",
      "updated_at": "2026-06-10T14:48:26Z",
      "duration_ms": 256000
    },
    {
      "id": 27284385429,
      "name": "Release (Golden Path)",
      "event": "push",
      "status": "completed",
      "conclusion": "failure",
      "created_at": "2026-06-10T14:44:10Z",
      "updated_at": "2026-06-10T15:04:39Z",
      "duration_ms": 1229000
    },
    {
      "id": 27284384730,
      "name": "Lock Tests (Production Sentinel)",
      "event": "push",
      "status": "completed",
      "conclusion": "failure",
      "created_at": "2026-06-10T14:44:09Z",
      "updated_at": "2026-06-10T14:53:30Z",
      "duration_ms": 561000
    },
    {
      "id": 27284380541,
      "name": ".github/workflows/ci.yml",
      "event": "push",
      "status": "completed",
      "conclusion": "failure",
      "created_at": "2026-06-10T14:44:06Z",
      "updated_at": "2026-06-10T14:44:06Z",
      "duration_ms": 0
    },
    {
      "id": 27284379290,
      "name": ".github/workflows/daily-ltdd-telemetry.yml",
      "event": "push",
      "status": "completed",
      "conclusion": "failure",
      "created_at": "2026-06-10T14:44:04Z",
      "updated_at": "2026-06-10T14:44:04Z",
      "duration_ms": 0
    },
    {
      "id": 27284377892,
      "name": ".github/workflows/ltdd-sync-branch-protection.yml",
      "event": "push",
      "status": "completed",
      "conclusion": "failure",
      "created_at": "2026-06-10T14:44:03Z",
      "updated_at": "2026-06-10T14:44:03Z",
      "duration_ms": 0
    },
    {
      "id": 27284376287,
      "name": ".github/workflows/hardening-gate.yml",
      "event": "push",
      "status": "completed",
      "conclusion": "failure",
      "created_at": "2026-06-10T14:44:01Z",
      "updated_at": "2026-06-10T14:44:01Z",
      "duration_ms": 0
    },
    {
      "id": 27283879892,
      "name": ".github/workflows/ltdd-sync-branch-protection.yml",
      "event": "push",
      "status": "completed",
      "conclusion": "failure",
      "created_at": "2026-06-10T14:36:03Z",
      "updated_at": "2026-06-10T14:36:03Z",
      "duration_ms": 0
    },
    {
      "id": 27283876764,
      "name": ".github/workflows/hardening-gate.yml",
      "event": "push",
      "status": "completed",
      "conclusion": "failure",
      "created_at": "2026-06-10T14:36:00Z",
      "updated_at": "2026-06-10T14:36:00Z",
      "duration_ms": 0
    },
    {
      "id": 27283874092,
      "name": ".github/workflows/daily-ltdd-telemetry.yml",
      "event": "push",
      "status": "completed",
      "conclusion": "failure",
      "created_at": "2026-06-10T14:35:58Z",
      "updated_at": "2026-06-10T14:35:58Z",
      "duration_ms": 0
    },
    {
      "id": 27283871661,
      "name": ".github/workflows/ci.yml",
      "event": "push",
      "status": "completed",
      "conclusion": "failure",
      "created_at": "2026-06-10T14:35:56Z",
      "updated_at": "2026-06-10T14:35:56Z",
      "duration_ms": 0
    },
    {
      "id": 27280582491,
      "name": "Prod Guardrails",
      "event": "push",
      "status": "completed",
      "conclusion": "failure",
      "created_at": "2026-06-10T13:42:54Z",
      "updated_at": "2026-06-10T13:46:58Z",
      "duration_ms": 244000
    },
    {
      "id": 27280582589,
      "name": "Lock Tests (Production Sentinel)",
      "event": "push",
      "status": "completed",
      "conclusion": "failure",
      "created_at": "2026-06-10T13:42:54Z",
      "updated_at": "2026-06-10T13:52:41Z",
      "duration_ms": 587000
    },
    {
      "id": 27280582844,
      "name": "Release (Golden Path)",
      "event": "push",
      "status": "completed",
      "conclusion": "failure",
      "created_at": "2026-06-10T13:42:54Z",
      "updated_at": "2026-06-10T14:01:40Z",
      "duration_ms": 1126000
    },
    {
      "id": 27280580262,
      "name": ".github/workflows/hardening-gate.yml",
      "event": "push",
      "status": "completed",
      "conclusion": "failure",
      "created_at": "2026-06-10T13:42:51Z",
      "updated_at": "2026-06-10T13:42:51Z",
      "duration_ms": 0
    },
    {
      "id": 27280579289,
      "name": ".github/workflows/ci.yml",
      "event": "push",
      "status": "completed",
      "conclusion": "failure",
      "created_at": "2026-06-10T13:42:50Z",
      "updated_at": "2026-06-10T13:42:50Z",
      "duration_ms": 0
    },
    {
      "id": 27280578330,
      "name": ".github/workflows/daily-ltdd-telemetry.yml",
      "event": "push",
      "status": "completed",
      "conclusion": "failure",
      "created_at": "2026-06-10T13:42:49Z",
      "updated_at": "2026-06-10T13:42:49Z",
      "duration_ms": 0
    },
    {
      "id": 27280577655,
      "name": ".github/workflows/ltdd-sync-branch-protection.yml",
      "event": "push",
      "status": "completed",
      "conclusion": "failure",
      "created_at": "2026-06-10T13:42:48Z",
      "updated_at": "2026-06-10T13:42:48Z",
      "duration_ms": 0
    },
    {
      "id": 27279512916,
      "name": "Ping (Actions Test)",
      "event": "push",
      "status": "completed",
      "conclusion": "success",
      "created_at": "2026-06-10T13:25:29Z",
      "updated_at": "2026-06-10T13:25:40Z",
      "duration_ms": 11000
    },
    {
      "id": 27279507269,
      "name": ".github/workflows/daily-ltdd-telemetry.yml",
      "event": "push",
      "status": "completed",
      "conclusion": "failure",
      "created_at": "2026-06-10T13:25:24Z",
      "updated_at": "2026-06-10T13:25:24Z",
      "duration_ms": 0
    },
    {
      "id": 27279505122,
      "name": ".github/workflows/hardening-gate.yml",
      "event": "push",
      "status": "completed",
      "conclusion": "failure",
      "created_at": "2026-06-10T13:25:22Z",
      "updated_at": "2026-06-10T13:25:22Z",
      "duration_ms": 0
    },
    {
      "id": 27279503270,
      "name": ".github/workflows/ci.yml",
      "event": "push",
      "status": "completed",
      "conclusion": "failure",
      "created_at": "2026-06-10T13:25:20Z",
      "updated_at": "2026-06-10T13:25:20Z",
      "duration_ms": 0
    },
    {
      "id": 27279500805,
      "name": ".github/workflows/ltdd-sync-branch-protection.yml",
      "event": "push",
      "status": "completed",
      "conclusion": "failure",
      "created_at": "2026-06-10T13:25:17Z",
      "updated_at": "2026-06-10T13:25:17Z",
      "duration_ms": 0
    },
    {
      "id": 27275220160,
      "name": "Release (Golden Path)",
      "event": "push",
      "status": "completed",
      "conclusion": "success",
      "created_at": "2026-06-10T12:10:07Z",
      "updated_at": "2026-06-10T12:33:18Z",
      "duration_ms": 1391000
    },
    {
      "id": 27275219775,
      "name": "Prod Guardrails",
      "event": "push",
      "status": "completed",
      "conclusion": "failure",
      "created_at": "2026-06-10T12:10:07Z",
      "updated_at": "2026-06-10T12:14:13Z",
      "duration_ms": 246000
    },
    {
      "id": 27275219779,
      "name": "Lock Tests (Production Sentinel)",
      "event": "push",
      "status": "completed",
      "conclusion": "failure",
      "created_at": "2026-06-10T12:10:07Z",
      "updated_at": "2026-06-10T12:20:42Z",
      "duration_ms": 635000
    },
    {
      "id": 27275217151,
      "name": ".github/workflows/hardening-gate.yml",
      "event": "push",
      "status": "completed",
      "conclusion": "failure",
      "created_at": "2026-06-10T12:10:04Z",
      "updated_at": "2026-06-10T12:10:04Z",
      "duration_ms": 0
    },
    {
      "id": 27275216150,
      "name": ".github/workflows/ltdd-sync-branch-protection.yml",
      "event": "push",
      "status": "completed",
      "conclusion": "failure",
      "created_at": "2026-06-10T12:10:02Z",
      "updated_at": "2026-06-10T12:10:02Z",
      "duration_ms": 0
    },
    {
      "id": 27275215292,
      "name": ".github/workflows/ci.yml",
      "event": "push",
      "status": "completed",
      "conclusion": "failure",
      "created_at": "2026-06-10T12:10:02Z",
      "updated_at": "2026-06-10T12:10:02Z",
      "duration_ms": 0
    },
    {
      "id": 27275214529,
      "name": ".github/workflows/daily-ltdd-telemetry.yml",
      "event": "push",
      "status": "completed",
      "conclusion": "failure",
      "created_at": "2026-06-10T12:10:01Z",
      "updated_at": "2026-06-10T12:10:01Z",
      "duration_ms": 0
    },
    {
      "id": 27274799037,
      "name": "Ping (Actions Test)",
      "event": "push",
      "status": "completed",
      "conclusion": "success",
      "created_at": "2026-06-10T12:02:17Z",
      "updated_at": "2026-06-10T12:02:26Z",
      "duration_ms": 9000
    },
    {
      "id": 27274796658,
      "name": ".github/workflows/ci.yml",
      "event": "push",
      "status": "completed",
      "conclusion": "failure",
      "created_at": "2026-06-10T12:02:14Z",
      "updated_at": "2026-06-10T12:02:14Z",
      "duration_ms": 0
    },
    {
      "id": 27274795666,
      "name": ".github/workflows/daily-ltdd-telemetry.yml",
      "event": "push",
      "status": "completed",
      "conclusion": "failure",
      "created_at": "2026-06-10T12:02:13Z",
      "updated_at": "2026-06-10T12:02:13Z",
      "duration_ms": 0
    },
    {
      "id": 27274794460,
      "name": ".github/workflows/hardening-gate.yml",
      "event": "push",
      "status": "completed",
      "conclusion": "failure",
      "created_at": "2026-06-10T12:02:11Z",
      "updated_at": "2026-06-10T12:02:11Z",
      "duration_ms": 0
    },
    {
      "id": 27274793169,
      "name": ".github/workflows/ltdd-sync-branch-protection.yml",
      "event": "push",
      "status": "completed",
      "conclusion": "failure",
      "created_at": "2026-06-10T12:02:10Z",
      "updated_at": "2026-06-10T12:02:10Z",
      "duration_ms": 0
    },
    {
      "id": 27272843709,
      "name": "Release (Golden Path)",
      "event": "push",
      "status": "completed",
      "conclusion": "success",
      "created_at": "2026-06-10T11:24:21Z",
      "updated_at": "2026-06-10T11:46:15Z",
      "duration_ms": 1314000
    },
    {
      "id": 27272843249,
      "name": "Lock Tests (Production Sentinel)",
      "event": "push",
      "status": "completed",
      "conclusion": "failure",
      "created_at": "2026-06-10T11:24:20Z",
      "updated_at": "2026-06-10T11:35:12Z",
      "duration_ms": 652000
    },
    {
      "id": 27272843498,
      "name": "Prod Guardrails",
      "event": "push",
      "status": "completed",
      "conclusion": "failure",
      "created_at": "2026-06-10T11:24:20Z",
      "updated_at": "2026-06-10T11:28:38Z",
      "duration_ms": 258000
    },
    {
      "id": 27272841620,
      "name": ".github/workflows/ci.yml",
      "event": "push",
      "status": "completed",
      "conclusion": "failure",
      "created_at": "2026-06-10T11:24:18Z",
      "updated_at": "2026-06-10T11:24:18Z",
      "duration_ms": 0
    },
    {
      "id": 27272840286,
      "name": ".github/workflows/daily-ltdd-telemetry.yml",
      "event": "push",
      "status": "completed",
      "conclusion": "failure",
      "created_at": "2026-06-10T11:24:17Z",
      "updated_at": "2026-06-10T11:24:17Z",
      "duration_ms": 0
    },
    {
      "id": 27272840953,
      "name": ".github/workflows/ltdd-sync-branch-protection.yml",
      "event": "push",
      "status": "completed",
      "conclusion": "failure",
      "created_at": "2026-06-10T11:24:17Z",
      "updated_at": "2026-06-10T11:24:17Z",
      "duration_ms": 0
    },
    {
      "id": 27272839731,
      "name": ".github/workflows/hardening-gate.yml",
      "event": "push",
      "status": "completed",
      "conclusion": "failure",
      "created_at": "2026-06-10T11:24:16Z",
      "updated_at": "2026-06-10T11:24:16Z",
      "duration_ms": 0
    },
    {
      "id": 27272449572,
      "name": "Ping (Actions Test)",
      "event": "push",
      "status": "completed",
      "conclusion": "success",
      "created_at": "2026-06-10T11:16:36Z",
      "updated_at": "2026-06-10T11:16:47Z",
      "duration_ms": 11000
    },
    {
      "id": 27272448164,
      "name": ".github/workflows/ci.yml",
      "event": "push",
      "status": "completed",
      "conclusion": "failure",
      "created_at": "2026-06-10T11:16:34Z",
      "updated_at": "2026-06-10T11:16:34Z",
      "duration_ms": 0
    },
    {
      "id": 27272446772,
      "name": ".github/workflows/ltdd-sync-branch-protection.yml",
      "event": "push",
      "status": "completed",
      "conclusion": "failure",
      "created_at": "2026-06-10T11:16:33Z",
      "updated_at": "2026-06-10T11:16:33Z",
      "duration_ms": 0
    },
    {
      "id": 27272447525,
      "name": ".github/workflows/hardening-gate.yml",
      "event": "push",
      "status": "completed",
      "conclusion": "failure",
      "created_at": "2026-06-10T11:16:33Z",
      "updated_at": "2026-06-10T11:16:33Z",
      "duration_ms": 0
    },
    {
      "id": 27272446048,
      "name": ".github/workflows/daily-ltdd-telemetry.yml",
      "event": "push",
      "status": "completed",
      "conclusion": "failure",
      "created_at": "2026-06-10T11:16:32Z",
      "updated_at": "2026-06-10T11:16:32Z",
      "duration_ms": 0
    }
  ]
}
